{
  "crawled_at": "2026-06-28T11:03:25.706066",
  "profile": "jupiter",
  "conditions": {
    "stations": [
      "吉祥寺",
      "江ノ島",
      "片瀬江ノ島",
      "茅ヶ崎",
      "荻窪",
      "西荻窪",
      "鎌倉",
      "阿佐ヶ谷"
    ],
    "min_area_sqm": 50,
    "max_age_years": 15,
    "max_rent_man": 15.0
  },
  "summary": {
    "rental_count": 6,
    "new_count": 0,
    "used_count": 46,
    "suumo_rental": 6,
    "suumo_new": 0,
    "suumo_used": 18,
    "suumo_used_ikkodate": 28,
    "homes_rental": 0,
    "homes_new": 0,
    "homes_used": 0,
    "cowcamo_used": 0
  },
  "station_stats": {
    "rental": {
      "江ノ島": {
        "count": 2,
        "avg_price": 9.65,
        "median_price": 9.65,
        "min_price": 9.4,
        "max_price": 9.9,
        "avg_price_per_sqm": 0.1753,
        "median_price_per_sqm": 0.1753,
        "p25_price_per_sqm": 0.1668,
        "p75_price_per_sqm": 0.1838,
        "avg_area": 55.245,
        "avg_age": 12,
        "avg_walk": 6.5,
        "new_listings": 2,
        "delisted": 0,
        "price_reduced": 0,
        "stale_count": 0
      },
      "鎌倉": {
        "count": 1,
        "avg_price": 13.5,
        "median_price": 13.5,
        "min_price": 13.5,
        "max_price": 13.5,
        "avg_price_per_sqm": 0.244,
        "median_price_per_sqm": 0.244,
        "p25_price_per_sqm": 0.244,
        "p75_price_per_sqm": 0.244,
        "avg_area": 55.32,
        "avg_age": 9,
        "avg_walk": 18,
        "new_listings": 1,
        "delisted": 3,
        "price_reduced": 0,
        "stale_count": 0
      },
      "茅ヶ崎": {
        "count": 3,
        "avg_price": 10.3333,
        "median_price": 8.1,
        "min_price": 8.1,
        "max_price": 14.8,
        "avg_price_per_sqm": 0.1854,
        "median_price_per_sqm": 0.1372,
        "p25_price_per_sqm": 0.1372,
        "p75_price_per_sqm": 0.2818,
        "avg_area": 56.86,
        "avg_age": 10,
        "avg_walk": 8.3333,
        "new_listings": 1,
        "delisted": 0,
        "price_reduced": 0,
        "stale_count": 0
      }
    },
    "new": {},
    "used": {
      "江ノ島": {
        "count": 20,
        "avg_price": 3269.55,
        "median_price": 3580.0,
        "min_price": 1980.0,
        "max_price": 4480.0,
        "avg_price_per_sqm": 36.9776,
        "median_price_per_sqm": 35.2886,
        "p25_price_per_sqm": 33.7725,
        "p75_price_per_sqm": 39.3148,
        "avg_area": 88.8815,
        "avg_age": 33.4,
        "avg_walk": 13.8,
        "new_listings": 0,
        "delisted": 0,
        "price_reduced": 0,
        "stale_count": 16
      },
      "茅ヶ崎": {
        "count": 19,
        "avg_price": 3394.7368,
        "median_price": 3398.0,
        "min_price": 2099.0,
        "max_price": 4480.0,
        "avg_price_per_sqm": 44.9853,
        "median_price_per_sqm": 44.0188,
        "p25_price_per_sqm": 35.1499,
        "p75_price_per_sqm": 49.8752,
        "avg_area": 76.5211,
        "avg_age": 23.8947,
        "avg_walk": 8.2105,
        "new_listings": 0,
        "delisted": 0,
        "price_reduced": 0,
        "stale_count": 15
      },
      "阿佐ヶ谷": {
        "count": 1,
        "avg_price": 3580.0,
        "median_price": 3580.0,
        "min_price": 3580.0,
        "max_price": 3580.0,
        "avg_price_per_sqm": 52.6238,
        "median_price_per_sqm": 52.6238,
        "p25_price_per_sqm": 52.6238,
        "p75_price_per_sqm": 52.6238,
        "avg_area": 68.03,
        "avg_age": 37,
        "avg_walk": 20,
        "new_listings": 0,
        "delisted": 0,
        "price_reduced": 0,
        "stale_count": 1
      },
      "鎌倉": {
        "count": 6,
        "avg_price": 4197.5,
        "median_price": 4397.0,
        "min_price": 3000.0,
        "max_price": 4497.0,
        "avg_price_per_sqm": 48.1116,
        "median_price_per_sqm": 51.2172,
        "p25_price_per_sqm": 51.2172,
        "p75_price_per_sqm": 52.3821,
        "avg_area": 88.0683,
        "avg_age": 17.8333,
        "avg_walk": 12.8333,
        "new_listings": 0,
        "delisted": 0,
        "price_reduced": 0,
        "stale_count": 6
      }
    }
  },
  "changes": {
    "price_reduced": [],
    "new_listings": [
      {
        "uid": "923e506e845b",
        "name": "レガシープレイス片瀬",
        "station": "江ノ島",
        "type": "rental",
        "price": 9.9,
        "detail_url": "https://suumo.jp/chintai/jnc_000108111560/"
      },
      {
        "uid": "6030cc1ed947",
        "name": "ＢＲＩＮＤＤＬＥ　ＣＯＵＲＴ",
        "station": "江ノ島",
        "type": "rental",
        "price": 9.4,
        "detail_url": "https://suumo.jp/chintai/jnc_000108111570/"
      },
      {
        "uid": "3f920859bfb5",
        "name": "リヴァージュ湘南II",
        "station": "鎌倉",
        "type": "rental",
        "price": 13.5,
        "detail_url": "https://suumo.jp/chintai/jnc_000108116887/"
      },
      {
        "uid": "80f726afd7d5",
        "name": "MAISON　DE　HINODE",
        "station": "茅ヶ崎",
        "type": "rental",
        "price": 14.8,
        "detail_url": "https://suumo.jp/chintai/jnc_000107946592/"
      }
    ],
    "delisted": [
      {
        "uid": "b7f370a3fd06",
        "name": "鎌倉材木座住宅",
        "station": "鎌倉",
        "type": "rental",
        "last_price": 14.9,
        "detail_url": "https://suumo.jp/chintai/jnc_000105330644/",
        "first_seen": "2026-03-22",
        "last_seen": "2026-06-27"
      },
      {
        "uid": "b6ac0d3b086e",
        "name": "マイカーサ北鎌倉",
        "station": "鎌倉",
        "type": "rental",
        "last_price": 14.6,
        "detail_url": "https://suumo.jp/chintai/jnc_000097956260/",
        "first_seen": "2026-05-10",
        "last_seen": "2026-06-27"
      },
      {
        "uid": "2a35bfa02dde",
        "name": "鎌倉材木座住宅",
        "station": "鎌倉",
        "type": "rental",
        "last_price": 14.4,
        "detail_url": "https://suumo.jp/chintai/jnc_000108080447/",
        "first_seen": "2026-06-27",
        "last_seen": "2026-06-27"
      }
    ],
    "stale": [
      {
        "uid": "04f4b1554a2d",
        "name": "◇ヴィラヴェール藤沢☆彡空室につき即入居可◎＃閑静な…",
        "station": "江ノ島",
        "type": "used",
        "days_listed": 73,
        "price": 1980.0,
        "detail_url": "https://suumo.jp/ms/chuko/kanagawa/sc_fujisawa/nc_78861704/"
      },
      {
        "uid": "6a2e2ee4f9db",
        "name": "六会駅前高層住宅",
        "station": "江ノ島",
        "type": "used",
        "days_listed": 90,
        "price": 1990.0,
        "detail_url": "https://suumo.jp/ms/chuko/kanagawa/sc_fujisawa/nc_79171635/"
      },
      {
        "uid": "b9f009dff4a4",
        "name": "藤沢西ガーデンハウス",
        "station": "江ノ島",
        "type": "used",
        "days_listed": 37,
        "price": 1998.0,
        "detail_url": "https://suumo.jp/ms/chuko/kanagawa/sc_fujisawa/nc_20884952/"
      },
      {
        "uid": "be3296622f97",
        "name": "六会駅前高層住宅",
        "station": "江ノ島",
        "type": "used",
        "days_listed": 16,
        "price": 2090.0,
        "detail_url": "https://suumo.jp/ms/chuko/kanagawa/sc_fujisawa/nc_21055118/"
      },
      {
        "uid": "fa4fcd06f141",
        "name": "オーベル湘南台",
        "station": "江ノ島",
        "type": "used",
        "days_listed": 29,
        "price": 2480.0,
        "detail_url": "https://suumo.jp/ms/chuko/kanagawa/sc_fujisawa/nc_20960842/"
      },
      {
        "uid": "42d88d9b3377",
        "name": "藤沢太平ハイツ１号棟",
        "station": "江ノ島",
        "type": "used",
        "days_listed": 90,
        "price": 2680.0,
        "detail_url": "https://suumo.jp/ms/chuko/kanagawa/sc_fujisawa/nc_20080385/"
      },
      {
        "uid": "13503bffc668",
        "name": "オクトス湘南茅ヶ崎グランドヒル",
        "station": "茅ヶ崎",
        "type": "used",
        "days_listed": 29,
        "price": 2380.0,
        "detail_url": "https://suumo.jp/ms/chuko/kanagawa/sc_chigasaki/nc_20960899/"
      },
      {
        "uid": "19761a0fa7d2",
        "name": "茅ヶ崎海岸松が丘ハイツ",
        "station": "茅ヶ崎",
        "type": "used",
        "days_listed": 35,
        "price": 2980.0,
        "detail_url": "https://suumo.jp/ms/chuko/kanagawa/sc_chigasaki/nc_20875611/"
      },
      {
        "uid": "fa569a53569f",
        "name": "茅ヶ崎グランドハイツB",
        "station": "茅ヶ崎",
        "type": "used",
        "days_listed": 92,
        "price": 2999.0,
        "detail_url": "https://suumo.jp/ms/chuko/kanagawa/sc_chigasaki/nc_20538628/"
      },
      {
        "uid": "9bb7fc77c7b6",
        "name": "茅ヶ崎グランドハイツ　Ｂ棟",
        "station": "茅ヶ崎",
        "type": "used",
        "days_listed": 21,
        "price": 3398.0,
        "detail_url": "https://suumo.jp/ms/chuko/kanagawa/sc_chigasaki/nc_20895771/"
      },
      {
        "uid": "17b1f5cf4d52",
        "name": "ライオンズマンション茅ヶ崎中央公園",
        "station": "茅ヶ崎",
        "type": "used",
        "days_listed": 100,
        "price": 3598.0,
        "detail_url": "https://suumo.jp/ms/chuko/kanagawa/sc_chigasaki/nc_77016659/"
      },
      {
        "uid": "6f73424cfaec",
        "name": "グラン・コート湘南茅ヶ崎",
        "station": "茅ヶ崎",
        "type": "used",
        "days_listed": 100,
        "price": 3650.0,
        "detail_url": "https://suumo.jp/ms/chuko/kanagawa/sc_chigasaki/nc_78544840/"
      },
      {
        "uid": "ff7eca0a42ee",
        "name": "ウェリス茅ヶ崎東海岸南",
        "station": "茅ヶ崎",
        "type": "used",
        "days_listed": 94,
        "price": 4180.0,
        "detail_url": "https://suumo.jp/ms/chuko/kanagawa/sc_chigasaki/nc_20520495/"
      },
      {
        "uid": "934bfcdcf313",
        "name": "ベルス茅ヶ崎東海岸",
        "station": "茅ヶ崎",
        "type": "used",
        "days_listed": 30,
        "price": 4480.0,
        "detail_url": "https://suumo.jp/ms/chuko/kanagawa/sc_chigasaki/nc_20949069/"
      },
      {
        "uid": "d4e7f7f1d4b4",
        "name": "",
        "station": "阿佐ヶ谷",
        "type": "used",
        "days_listed": 86,
        "price": 3580.0,
        "detail_url": "https://suumo.jp/chukoikkodate/tokyo/sc_suginami/nc_20576937/"
      },
      {
        "uid": "23b38b3a643f",
        "name": "",
        "station": "江ノ島",
        "type": "used",
        "days_listed": 57,
        "price": 3190.0,
        "detail_url": "https://suumo.jp/chukoikkodate/kanagawa/sc_fujisawa/nc_20770757/"
      },
      {
        "uid": "7ec24ee10d30",
        "name": "藤沢市善行5丁目",
        "station": "江ノ島",
        "type": "used",
        "days_listed": 47,
        "price": 3190.0,
        "detail_url": "https://suumo.jp/chukoikkodate/kanagawa/sc_fujisawa/nc_20732133/"
      },
      {
        "uid": "e133a8ec4ff4",
        "name": "",
        "station": "江ノ島",
        "type": "used",
        "days_listed": 69,
        "price": 3700.0,
        "detail_url": "https://suumo.jp/chukoikkodate/kanagawa/sc_fujisawa/nc_20699913/"
      },
      {
        "uid": "3efcbc0b8947",
        "name": "陽当たりの良い南西道路に面した４ＬＤＫ戸建登場！！",
        "station": "江ノ島",
        "type": "used",
        "days_listed": 90,
        "price": 3730.0,
        "detail_url": "https://suumo.jp/chukoikkodate/kanagawa/sc_fujisawa/nc_78520446/"
      },
      {
        "uid": "680360a122df",
        "name": "藤沢市白旗2丁目　中古戸建",
        "station": "江ノ島",
        "type": "used",
        "days_listed": 88,
        "price": 4480.0,
        "detail_url": "https://suumo.jp/chukoikkodate/kanagawa/sc_fujisawa/nc_20392305/"
      },
      {
        "uid": "140f4a740056",
        "name": "敷地面積８８．４６坪。JR横須賀線「北鎌倉」駅徒歩９…",
        "station": "鎌倉",
        "type": "used",
        "days_listed": 90,
        "price": 3000.0,
        "detail_url": "https://suumo.jp/chukoikkodate/kanagawa/sc_kamakura/nc_72168930/"
      },
      {
        "uid": "0b8d48fabfd5",
        "name": "",
        "station": "江ノ島",
        "type": "used",
        "days_listed": 90,
        "price": 3999.0,
        "detail_url": "https://suumo.jp/chukoikkodate/kanagawa/sc_kamakura/nc_77465233/"
      },
      {
        "uid": "c435fcaf162f",
        "name": "",
        "station": "江ノ島",
        "type": "used",
        "days_listed": 90,
        "price": 3999.0,
        "detail_url": "https://suumo.jp/chukoikkodate/kanagawa/sc_kamakura/nc_76761542/"
      },
      {
        "uid": "3de7c3abdb47",
        "name": "鎌倉市笛田6丁目　中古戸建",
        "station": "江ノ島",
        "type": "used",
        "days_listed": 90,
        "price": 3999.0,
        "detail_url": "https://suumo.jp/chukoikkodate/kanagawa/sc_kamakura/nc_79144475/"
      },
      {
        "uid": "3c73cde6c7f3",
        "name": "",
        "station": "江ノ島",
        "type": "used",
        "days_listed": 60,
        "price": 3999.0,
        "detail_url": "https://suumo.jp/chukoikkodate/kanagawa/sc_kamakura/nc_78810496/"
      },
      {
        "uid": "be179cd7cdd7",
        "name": "",
        "station": "江ノ島",
        "type": "used",
        "days_listed": 38,
        "price": 4280.0,
        "detail_url": "https://suumo.jp/chukoikkodate/kanagawa/sc_kamakura/nc_20893257/"
      },
      {
        "uid": "5ee4bf78295c",
        "name": "リフォーム済×築8年×室内美邸♪×鎌倉市手広2丁目【…",
        "station": "鎌倉",
        "type": "used",
        "days_listed": 62,
        "price": 4397.0,
        "detail_url": "https://suumo.jp/chukoikkodate/kanagawa/sc_kamakura/nc_20737822/"
      },
      {
        "uid": "6d537a752bee",
        "name": "◇◆鎌倉市手広２丁目　中古戸建◆◇",
        "station": "鎌倉",
        "type": "used",
        "days_listed": 77,
        "price": 4397.0,
        "detail_url": "https://suumo.jp/chukoikkodate/kanagawa/sc_kamakura/nc_20640423/"
      },
      {
        "uid": "9379fb3e33cc",
        "name": "【鎌倉市手広2丁目】",
        "station": "鎌倉",
        "type": "used",
        "days_listed": 65,
        "price": 4397.0,
        "detail_url": "https://suumo.jp/chukoikkodate/kanagawa/sc_kamakura/nc_20676500/"
      },
      {
        "uid": "fbafb6ca85af",
        "name": "鎌倉市手広2丁目　中古戸建て",
        "station": "鎌倉",
        "type": "used",
        "days_listed": 90,
        "price": 4497.0,
        "detail_url": "https://suumo.jp/chukoikkodate/kanagawa/sc_kamakura/nc_20327554/"
      },
      {
        "uid": "d08db7ca4b49",
        "name": "鎌倉市手広2丁目　中古戸建",
        "station": "鎌倉",
        "type": "used",
        "days_listed": 14,
        "price": 4497.0,
        "detail_url": "https://suumo.jp/chukoikkodate/kanagawa/sc_kamakura/nc_21067737/"
      },
      {
        "uid": "8b72cbe26e87",
        "name": "☆落ち着いた住環境が魅力☆茅ヶ崎市高田戸建",
        "station": "茅ヶ崎",
        "type": "used",
        "days_listed": 100,
        "price": 2580.0,
        "detail_url": "https://suumo.jp/chukoikkodate/kanagawa/sc_chigasaki/nc_78194710/"
      },
      {
        "uid": "d5adc7b44f03",
        "name": "海近と生活利便性が交わる立地。コストパフォーマンスの…",
        "station": "茅ヶ崎",
        "type": "used",
        "days_listed": 30,
        "price": 2999.0,
        "detail_url": "https://suumo.jp/chukoikkodate/kanagawa/sc_chigasaki/nc_20957096/"
      },
      {
        "uid": "dbb97ae3ddc9",
        "name": "【緑の潤いと静寂に包まれる暮らし。光と風が抜ける家】…",
        "station": "茅ヶ崎",
        "type": "used",
        "days_listed": 62,
        "price": 3280.0,
        "detail_url": "https://suumo.jp/chukoikkodate/kanagawa/sc_chigasaki/nc_20735865/"
      },
      {
        "uid": "865f42d3ca14",
        "name": "茅ヶ崎市茅ヶ崎戸建",
        "station": "茅ヶ崎",
        "type": "used",
        "days_listed": 100,
        "price": 3580.0,
        "detail_url": "https://suumo.jp/chukoikkodate/kanagawa/sc_chigasaki/nc_78393172/"
      },
      {
        "uid": "c289839b7128",
        "name": "茅ヶ崎萩園トヨタホーム設計施工の注文住宅",
        "station": "茅ヶ崎",
        "type": "used",
        "days_listed": 100,
        "price": 3878.0,
        "detail_url": "https://suumo.jp/chukoikkodate/kanagawa/sc_chigasaki/nc_20453735/"
      },
      {
        "uid": "063e77b3957c",
        "name": "オープンセレクション茅ヶ崎",
        "station": "茅ヶ崎",
        "type": "used",
        "days_listed": 47,
        "price": 3980.0,
        "detail_url": "https://suumo.jp/chukoikkodate/kanagawa/sc_chigasaki/nc_77679410/"
      },
      {
        "uid": "7118420ee33b",
        "name": "オープンセレクション茅ケ崎",
        "station": "茅ヶ崎",
        "type": "used",
        "days_listed": 80,
        "price": 4380.0,
        "detail_url": "https://suumo.jp/chukoikkodate/kanagawa/sc_chigasaki/nc_78698949/"
      }
    ],
    "station_summary": {
      "荻窪": {
        "rental": {
          "new_count": 0,
          "delisted_count": 0,
          "price_reduced_count": 0,
          "stale_count": 0
        },
        "new": {
          "new_count": 0,
          "delisted_count": 0,
          "price_reduced_count": 0,
          "stale_count": 0
        },
        "used": {
          "new_count": 0,
          "delisted_count": 0,
          "price_reduced_count": 0,
          "stale_count": 0
        }
      },
      "阿佐ヶ谷": {
        "rental": {
          "new_count": 0,
          "delisted_count": 0,
          "price_reduced_count": 0,
          "stale_count": 0
        },
        "new": {
          "new_count": 0,
          "delisted_count": 0,
          "price_reduced_count": 0,
          "stale_count": 0
        },
        "used": {
          "new_count": 0,
          "delisted_count": 0,
          "price_reduced_count": 0,
          "stale_count": 1
        }
      },
      "西荻窪": {
        "rental": {
          "new_count": 0,
          "delisted_count": 0,
          "price_reduced_count": 0,
          "stale_count": 0
        },
        "new": {
          "new_count": 0,
          "delisted_count": 0,
          "price_reduced_count": 0,
          "stale_count": 0
        },
        "used": {
          "new_count": 0,
          "delisted_count": 0,
          "price_reduced_count": 0,
          "stale_count": 0
        }
      },
      "江ノ島": {
        "rental": {
          "new_count": 2,
          "delisted_count": 0,
          "price_reduced_count": 0,
          "stale_count": 0
        },
        "new": {
          "new_count": 0,
          "delisted_count": 0,
          "price_reduced_count": 0,
          "stale_count": 0
        },
        "used": {
          "new_count": 0,
          "delisted_count": 0,
          "price_reduced_count": 0,
          "stale_count": 16
        }
      },
      "鎌倉": {
        "rental": {
          "new_count": 1,
          "delisted_count": 3,
          "price_reduced_count": 0,
          "stale_count": 0
        },
        "new": {
          "new_count": 0,
          "delisted_count": 0,
          "price_reduced_count": 0,
          "stale_count": 0
        },
        "used": {
          "new_count": 0,
          "delisted_count": 0,
          "price_reduced_count": 0,
          "stale_count": 6
        }
      },
      "吉祥寺": {
        "rental": {
          "new_count": 0,
          "delisted_count": 0,
          "price_reduced_count": 0,
          "stale_count": 0
        },
        "new": {
          "new_count": 0,
          "delisted_count": 0,
          "price_reduced_count": 0,
          "stale_count": 0
        },
        "used": {
          "new_count": 0,
          "delisted_count": 0,
          "price_reduced_count": 0,
          "stale_count": 0
        }
      },
      "茅ヶ崎": {
        "rental": {
          "new_count": 1,
          "delisted_count": 0,
          "price_reduced_count": 0,
          "stale_count": 0
        },
        "new": {
          "new_count": 0,
          "delisted_count": 0,
          "price_reduced_count": 0,
          "stale_count": 0
        },
        "used": {
          "new_count": 0,
          "delisted_count": 0,
          "price_reduced_count": 0,
          "stale_count": 15
        }
      },
      "片瀬江ノ島": {
        "rental": {
          "new_count": 0,
          "delisted_count": 0,
          "price_reduced_count": 0,
          "stale_count": 0
        },
        "new": {
          "new_count": 0,
          "delisted_count": 0,
          "price_reduced_count": 0,
          "stale_count": 0
        },
        "used": {
          "new_count": 0,
          "delisted_count": 0,
          "price_reduced_count": 0,
          "stale_count": 0
        }
      }
    },
    "summary": {
      "total_new": 4,
      "total_delisted": 3,
      "total_price_reduced": 0,
      "total_stale": 38
    }
  },
  "rental": [
    {
      "source": "SUUMO",
      "type": "賃貸",
      "name": "レガシープレイス片瀬",
      "detail_url": "https://suumo.jp/chintai/jnc_000108111560/",
      "price": 9.9,
      "price_text": "9.9万円3000円",
      "management_fee": 9.9,
      "management_fee_text": "9.9万円9.9万円",
      "area": 59.34,
      "area_text": "59.34m²",
      "walk_minutes": 8,
      "walk_text": "江ノ島駅",
      "station": "江ノ島",
      "age_years": 9,
      "age_text": "築9年",
      "image_url": "https://img01.suumo.com/front/gazo/fr/bukken/837/100514015837/100514015837_go.jpg",
      "address": "神奈川県藤沢市片瀬２",
      "access": "江ノ島電鉄線/柳小路駅 歩8分 / 湘南モノレール/湘南江の島駅 歩17分 / ＪＲ東海道本線/藤沢駅 歩20分"
    },
    {
      "source": "SUUMO",
      "type": "賃貸",
      "name": "ＢＲＩＮＤＤＬＥ　ＣＯＵＲＴ",
      "detail_url": "https://suumo.jp/chintai/jnc_000108111570/",
      "price": 9.4,
      "price_text": "9.4万円5000円",
      "management_fee": 9.4,
      "management_fee_text": "9.4万円9.4万円",
      "area": 51.15,
      "area_text": "51.15m²",
      "walk_minutes": 5,
      "walk_text": "江ノ島駅",
      "station": "江ノ島",
      "age_years": 15,
      "age_text": "築15年",
      "image_url": "https://img01.suumo.com/front/gazo/fr/bukken/952/100514017952/100514017952_go.jpg",
      "address": "神奈川県藤沢市藤沢２",
      "access": "小田急江ノ島線/藤沢本町駅 歩5分 / 小田急江ノ島線/藤沢駅 歩16分 / 小田急江ノ島線/善行駅 歩28分"
    },
    {
      "source": "SUUMO",
      "type": "賃貸",
      "name": "リヴァージュ湘南II",
      "detail_url": "https://suumo.jp/chintai/jnc_000108116887/",
      "price": 13.5,
      "price_text": "13.5万円4000円",
      "management_fee": 13.5,
      "management_fee_text": "13.5万円13.5万円",
      "area": 55.32,
      "area_text": "55.32m²",
      "walk_minutes": 18,
      "walk_text": "鎌倉駅",
      "station": "鎌倉",
      "age_years": 9,
      "age_text": "築9年",
      "image_url": "https://img01.suumo.com/front/gazo/fr/bukken/758/100514048758/100514048758_go.jpg",
      "address": "神奈川県鎌倉市材木座３",
      "access": "ＪＲ横須賀線/鎌倉駅 歩18分 / 江ノ島電鉄線/和田塚駅 歩17分 / 江ノ島電鉄線/由比ヶ浜駅 歩16分"
    },
    {
      "source": "SUUMO",
      "type": "賃貸",
      "name": "MAISON　DE　HINODE",
      "detail_url": "https://suumo.jp/chintai/jnc_000107946592/",
      "price": 14.8,
      "price_text": "14.8万円8500円",
      "management_fee": 14.8,
      "management_fee_text": "14.8万円29.6万円",
      "area": 52.52,
      "area_text": "52.52m²",
      "walk_minutes": 5,
      "walk_text": "茅ヶ崎駅",
      "station": "茅ヶ崎",
      "age_years": 0,
      "age_text": "新築",
      "image_url": "https://img01.suumo.com/front/gazo/fr/bukken/269/100510466269/100510466269_go.jpg",
      "address": "神奈川県茅ヶ崎市中海岸１",
      "access": "ＪＲ東海道本線/茅ケ崎駅 歩5分 / ＪＲ相模線/北茅ケ崎駅 歩20分 / "
    },
    {
      "source": "SUUMO",
      "type": "賃貸",
      "name": "メゾンド・デスパシオ",
      "detail_url": "https://suumo.jp/chintai/jnc_000107994097/",
      "price": 8.1,
      "price_text": "8.1万円4100円",
      "management_fee": 12.1,
      "management_fee_text": "-12.1万円",
      "area": 59.03,
      "area_text": "59.03m²",
      "walk_minutes": 10,
      "walk_text": "茅ヶ崎駅",
      "station": "茅ヶ崎",
      "age_years": 15,
      "age_text": "築15年",
      "image_url": "https://img01.suumo.com/front/gazo/fr/bukken/784/100513587784/100513587784_go.jpg",
      "address": "神奈川県茅ヶ崎市みずき１",
      "access": "ＪＲ相模線/香川駅 歩8分 / ＪＲ東海道本線/茅ケ崎駅 バス25分 (バス停)湘南みずき 歩10分 / ＪＲ相模線/寒川駅 歩21分"
    },
    {
      "source": "SUUMO",
      "type": "賃貸",
      "name": "ＪＲ相模線 香川駅 2階建 築15年",
      "detail_url": "https://suumo.jp/chintai/jnc_000108048698/",
      "price": 8.1,
      "price_text": "8.1万円4100円",
      "management_fee": 12.1,
      "management_fee_text": "-12.1万円",
      "area": 59.03,
      "area_text": "59.03m²",
      "walk_minutes": 10,
      "walk_text": "茅ヶ崎駅",
      "station": "茅ヶ崎",
      "age_years": 15,
      "age_text": "築15年",
      "image_url": "https://img01.suumo.com/front/gazo/fr/bukken/363/100513459363/100513459363_go.jpg",
      "address": "神奈川県茅ヶ崎市みずき１",
      "access": "ＪＲ相模線/香川駅 歩8分 / ＪＲ東海道本線/茅ケ崎駅 バス25分 (バス停)湘南みずき 歩10分 / ＪＲ相模線/寒川駅 歩21分"
    }
  ],
  "new": [],
  "used": [
    {
      "source": "SUUMO",
      "type": "中古",
      "name": "◇ヴィラヴェール藤沢☆彡空室につき即入居可◎＃閑静な…",
      "detail_url": "https://suumo.jp/ms/chuko/kanagawa/sc_fujisawa/nc_78861704/",
      "price": 1980.0,
      "price_text": "1980万円",
      "area": 65.7,
      "area_text": "65.7m2（19.87坪）（壁芯）",
      "walk_minutes": 14,
      "walk_text": "江ノ島駅 徒歩14分",
      "station": "江ノ島",
      "age_years": 31,
      "age_text": "1995年3月",
      "image_url": "https://img01.suumo.com/jj/resizeImage?src=gazo%2Fbukken%2F030%2FN010000%2Fimg%2F704%2F78861704%2F78861704_0175.jpg&w=192&h=144",
      "address": "神奈川県藤沢市稲荷１",
      "access": "小田急江ノ島線「藤沢本町」徒歩14分"
    },
    {
      "source": "SUUMO",
      "type": "中古",
      "name": "六会駅前高層住宅",
      "detail_url": "https://suumo.jp/ms/chuko/kanagawa/sc_fujisawa/nc_79171635/",
      "price": 1990.0,
      "price_text": "1990万円",
      "area": 64.96,
      "area_text": "64.96m2（19.65坪）（壁芯）",
      "walk_minutes": 7,
      "walk_text": "江ノ島駅 徒歩7分",
      "station": "江ノ島",
      "age_years": 52,
      "age_text": "1974年12月",
      "image_url": "https://img01.suumo.com/jj/resizeImage?src=gazo%2Fbukken%2F030%2FN010000%2Fimg%2F635%2F79171635%2F79171635_0020.jpg&w=192&h=144",
      "address": "神奈川県藤沢市亀井野１",
      "access": "小田急江ノ島線「六会日大前」徒歩7分"
    },
    {
      "source": "SUUMO",
      "type": "中古",
      "name": "藤沢西ガーデンハウス",
      "detail_url": "https://suumo.jp/ms/chuko/kanagawa/sc_fujisawa/nc_20884952/",
      "price": 1998.0,
      "price_text": "1998万円",
      "area": 65.14,
      "area_text": "65.14m2（19.70坪）（壁芯）",
      "walk_minutes": 4,
      "walk_text": "江ノ島駅",
      "station": "江ノ島",
      "age_years": 34,
      "age_text": "1992年4月",
      "image_url": "https://img01.suumo.com/jj/resizeImage?src=gazo%2Fbukken%2F030%2FN010000%2Fimg%2F952%2F20884952%2F20884952_0020.jpg&w=192&h=144",
      "address": "神奈川県藤沢市大庭",
      "access": "小田急江ノ島線「善行」バス9分停歩4分"
    },
    {
      "source": "SUUMO",
      "type": "中古",
      "name": "六会駅前高層住宅",
      "detail_url": "https://suumo.jp/ms/chuko/kanagawa/sc_fujisawa/nc_21055118/",
      "price": 2090.0,
      "price_text": "2090万円",
      "area": 61.63,
      "area_text": "61.63m2（18.64坪）（壁芯）",
      "walk_minutes": 5,
      "walk_text": "江ノ島駅 徒歩5分",
      "station": "江ノ島",
      "age_years": 52,
      "age_text": "1974年12月",
      "image_url": "https://img01.suumo.com/jj/resizeImage?src=gazo%2Fbukken%2F030%2FN010000%2Fimg%2F118%2F21055118%2F21055118_0012.jpg&w=192&h=144",
      "address": "神奈川県藤沢市亀井野１",
      "access": "小田急江ノ島線「六会日大前」徒歩5分"
    },
    {
      "source": "SUUMO",
      "type": "中古",
      "name": "オーベル湘南台",
      "detail_url": "https://suumo.jp/ms/chuko/kanagawa/sc_fujisawa/nc_20960842/",
      "price": 2480.0,
      "price_text": "2480万円",
      "area": 63.35,
      "area_text": "63.35m2（壁芯）",
      "walk_minutes": 3,
      "walk_text": "江ノ島駅",
      "station": "江ノ島",
      "age_years": 31,
      "age_text": "1995年9月",
      "image_url": "https://img01.suumo.com/jj/resizeImage?src=gazo%2Fbukken%2F030%2FN010000%2Fimg%2F842%2F20960842%2F20960842_0040.jpg&w=192&h=144",
      "address": "神奈川県藤沢市石川５-9‐15",
      "access": "小田急江ノ島線「湘南台」バス14分停歩3分"
    },
    {
      "source": "SUUMO",
      "type": "中古",
      "name": "湘南台ブラウンハイム",
      "detail_url": "https://suumo.jp/ms/chuko/kanagawa/sc_fujisawa/nc_21142370/",
      "price": 2650.0,
      "price_text": "2650万円",
      "area": 76.35,
      "area_text": "76.35m2（壁芯）",
      "walk_minutes": 8,
      "walk_text": "江ノ島駅 徒歩8分",
      "station": "江ノ島",
      "age_years": 47,
      "age_text": "1979年9月",
      "image_url": "https://img01.suumo.com/jj/resizeImage?src=gazo%2Fbukken%2F030%2FN010000%2Fimg%2F370%2F21142370%2F21142370_0013.jpg&w=192&h=144",
      "address": "神奈川県藤沢市湘南台４",
      "access": "小田急江ノ島線「湘南台」徒歩8分"
    },
    {
      "source": "SUUMO",
      "type": "中古",
      "name": "藤沢太平ハイツ１号棟",
      "detail_url": "https://suumo.jp/ms/chuko/kanagawa/sc_fujisawa/nc_20080385/",
      "price": 2680.0,
      "price_text": "2680万円",
      "area": 71.03,
      "area_text": "71.03m2（壁芯）",
      "walk_minutes": 16,
      "walk_text": "江ノ島駅 徒歩16分",
      "station": "江ノ島",
      "age_years": 49,
      "age_text": "1977年7月",
      "image_url": "https://img01.suumo.com/jj/resizeImage?src=gazo%2Fbukken%2F030%2FN010000%2Fimg%2F385%2F20080385%2F20080385_0023.jpg&w=192&h=144",
      "address": "神奈川県藤沢市辻堂太平台２",
      "access": "小田急江ノ島線「本鵠沼」徒歩16分"
    },
    {
      "source": "SUUMO",
      "type": "中古",
      "name": "茅ヶ崎ガーデンハウス",
      "detail_url": "https://suumo.jp/ms/chuko/kanagawa/sc_chigasaki/nc_21106846/",
      "price": 2099.0,
      "price_text": "2099万円",
      "area": 62.45,
      "area_text": "62.45m2（18.89坪）（壁芯）",
      "walk_minutes": 3,
      "walk_text": "茅ヶ崎駅",
      "station": "茅ヶ崎",
      "age_years": 38,
      "age_text": "1988年2月",
      "image_url": "https://img01.suumo.com/jj/resizeImage?src=gazo%2Fbukken%2F030%2FN010000%2Fimg%2F846%2F21106846%2F21106846_0004.jpg&w=192&h=144",
      "address": "神奈川県茅ヶ崎市柳島１",
      "access": "ＪＲ東海道本線「茅ケ崎」バス11分停歩3分"
    },
    {
      "source": "SUUMO",
      "type": "中古",
      "name": "オクトス湘南茅ヶ崎グランドヒル",
      "detail_url": "https://suumo.jp/ms/chuko/kanagawa/sc_chigasaki/nc_20960899/",
      "price": 2380.0,
      "price_text": "2380万円",
      "area": 67.71,
      "area_text": "67.71m2（20.48坪）（壁芯）",
      "walk_minutes": 1,
      "walk_text": "茅ヶ崎駅",
      "station": "茅ヶ崎",
      "age_years": 27,
      "age_text": "1999年10月",
      "image_url": "https://img01.suumo.com/jj/resizeImage?src=gazo%2Fbukken%2F030%2FN010000%2Fimg%2F899%2F20960899%2F20960899_0015.jpg&w=192&h=144",
      "address": "神奈川県茅ヶ崎市甘沼",
      "access": "ＪＲ東海道本線「茅ケ崎」バス13分停歩1分"
    },
    {
      "source": "SUUMO",
      "type": "中古",
      "name": "コスモ茅ヶ崎プレシオ",
      "detail_url": "https://suumo.jp/ms/chuko/kanagawa/sc_chigasaki/nc_21106732/",
      "price": 2599.0,
      "price_text": "2599万円",
      "area": 86.7,
      "area_text": "86.7m2（26.22坪）（壁芯）",
      "walk_minutes": 4,
      "walk_text": "茅ヶ崎駅",
      "station": "茅ヶ崎",
      "age_years": 37,
      "age_text": "1989年4月",
      "image_url": "https://img01.suumo.com/jj/resizeImage?src=gazo%2Fbukken%2F030%2FN010000%2Fimg%2F732%2F21106732%2F21106732_0005.jpg&w=192&h=144",
      "address": "神奈川県茅ヶ崎市今宿",
      "access": "ＪＲ東海道本線「茅ケ崎」バス7分停歩4分"
    },
    {
      "source": "SUUMO",
      "type": "中古",
      "name": "茅ヶ崎海岸松が丘ハイツ",
      "detail_url": "https://suumo.jp/ms/chuko/kanagawa/sc_chigasaki/nc_20875611/",
      "price": 2980.0,
      "price_text": "2980万円",
      "area": 74.87,
      "area_text": "74.87m2",
      "walk_minutes": 7,
      "walk_text": "茅ヶ崎駅",
      "station": "茅ヶ崎",
      "age_years": 49,
      "age_text": "1977年9月",
      "image_url": "https://img01.suumo.com/jj/resizeImage?src=gazo%2Fbukken%2F030%2FN010000%2Fimg%2F611%2F20875611%2F20875611_0017.jpg&w=192&h=144",
      "address": "神奈川県茅ヶ崎市松が丘２",
      "access": "ＪＲ東海道本線「茅ケ崎」バス7分停歩7分"
    },
    {
      "source": "SUUMO",
      "type": "中古",
      "name": "茅ヶ崎グランドハイツB",
      "detail_url": "https://suumo.jp/ms/chuko/kanagawa/sc_chigasaki/nc_20538628/",
      "price": 2999.0,
      "price_text": "2999万円",
      "area": 68.13,
      "area_text": "68.13m2（壁芯）",
      "walk_minutes": 10,
      "walk_text": "茅ヶ崎駅 徒歩10分",
      "station": "茅ヶ崎",
      "age_years": 40,
      "age_text": "1986年3月",
      "image_url": "https://img01.suumo.com/jj/resizeImage?src=gazo%2Fbukken%2F030%2FN010000%2Fimg%2F628%2F20538628%2F20538628_0050.jpg&w=192&h=144",
      "address": "神奈川県茅ヶ崎市本村５",
      "access": "ＪＲ相模線「北茅ケ崎」徒歩10分"
    },
    {
      "source": "SUUMO",
      "type": "中古",
      "name": "茅ヶ崎グランドハイツ　Ｂ棟",
      "detail_url": "https://suumo.jp/ms/chuko/kanagawa/sc_chigasaki/nc_20895771/",
      "price": 3398.0,
      "price_text": "3398万円",
      "area": 68.13,
      "area_text": "68.13m2（壁芯）",
      "walk_minutes": 19,
      "walk_text": "茅ヶ崎駅 徒歩19分",
      "station": "茅ヶ崎",
      "age_years": 40,
      "age_text": "1986年3月",
      "image_url": "https://img01.suumo.com/jj/resizeImage?src=gazo%2Fbukken%2F030%2FN010000%2Fimg%2F771%2F20895771%2F20895771_0001.jpg&w=192&h=144",
      "address": "神奈川県茅ヶ崎市本村５",
      "access": "ＪＲ東海道本線「茅ケ崎」徒歩19分"
    },
    {
      "source": "SUUMO",
      "type": "中古",
      "name": "ライオンズマンション茅ヶ崎中央公園",
      "detail_url": "https://suumo.jp/ms/chuko/kanagawa/sc_chigasaki/nc_77016659/",
      "price": 3598.0,
      "price_text": "3598万円",
      "area": 76.86,
      "area_text": "76.86m2（壁芯）",
      "walk_minutes": 10,
      "walk_text": "茅ヶ崎駅 徒歩10分",
      "station": "茅ヶ崎",
      "age_years": 34,
      "age_text": "1992年8月",
      "image_url": "https://img01.suumo.com/jj/resizeImage?src=gazo%2Fbukken%2F030%2FN010000%2Fimg%2F659%2F77016659%2F77016659_0001.jpg&w=192&h=144",
      "address": "神奈川県茅ヶ崎市本村４",
      "access": "ＪＲ東海道本線「茅ケ崎」徒歩10分"
    },
    {
      "source": "SUUMO",
      "type": "中古",
      "name": "グラン・コート湘南茅ヶ崎",
      "detail_url": "https://suumo.jp/ms/chuko/kanagawa/sc_chigasaki/nc_78544840/",
      "price": 3650.0,
      "price_text": "3650万円",
      "area": 75.1,
      "area_text": "75.1m2（壁芯）",
      "walk_minutes": 17,
      "walk_text": "茅ヶ崎駅 徒歩17分",
      "station": "茅ヶ崎",
      "age_years": 20,
      "age_text": "2006年3月",
      "image_url": "https://img01.suumo.com/jj/resizeImage?src=gazo%2Fbukken%2F030%2FN010000%2Fimg%2F840%2F78544840%2F78544840_0001.jpg&w=192&h=144",
      "address": "神奈川県茅ヶ崎市本村４",
      "access": "ＪＲ東海道本線「茅ケ崎」徒歩17分"
    },
    {
      "source": "SUUMO",
      "type": "中古",
      "name": "ウェリス茅ヶ崎東海岸南",
      "detail_url": "https://suumo.jp/ms/chuko/kanagawa/sc_chigasaki/nc_20520495/",
      "price": 4180.0,
      "price_text": "4180万円",
      "area": 62.72,
      "area_text": "62.72m2（壁芯）",
      "walk_minutes": 16,
      "walk_text": "茅ヶ崎駅 徒歩16分",
      "station": "茅ヶ崎",
      "age_years": 14,
      "age_text": "2012年5月",
      "image_url": "https://img01.suumo.com/jj/resizeImage?src=gazo%2Fbukken%2F030%2FN010000%2Fimg%2F495%2F20520495%2F20520495_0046.jpg&w=192&h=144",
      "address": "神奈川県茅ヶ崎市東海岸南１",
      "access": "ＪＲ東海道本線「茅ケ崎」徒歩16分"
    },
    {
      "source": "SUUMO",
      "type": "中古",
      "name": "パークホームズ湘南茅ヶ崎海岸",
      "detail_url": "https://suumo.jp/ms/chuko/kanagawa/sc_chigasaki/nc_21127320/",
      "price": 4280.0,
      "price_text": "4280万円",
      "area": 72.41,
      "area_text": "72.41m2",
      "walk_minutes": 2,
      "walk_text": "茅ヶ崎駅",
      "station": "茅ヶ崎",
      "age_years": 22,
      "age_text": "2004年10月",
      "image_url": "https://img01.suumo.com/jj/resizeImage?src=gazo%2Fbukken%2F030%2FN010000%2Fimg%2F320%2F21127320%2F21127320_0009.jpg&w=192&h=144",
      "address": "神奈川県茅ヶ崎市汐見台",
      "access": "ＪＲ東海道本線「茅ケ崎」バス10分停歩2分"
    },
    {
      "source": "SUUMO",
      "type": "中古",
      "name": "ベルス茅ヶ崎東海岸",
      "detail_url": "https://suumo.jp/ms/chuko/kanagawa/sc_chigasaki/nc_20949069/",
      "price": 4480.0,
      "price_text": "4480万円",
      "area": 65.35,
      "area_text": "65.35m2（壁芯）",
      "walk_minutes": 11,
      "walk_text": "茅ヶ崎駅 徒歩11分",
      "station": "茅ヶ崎",
      "age_years": 23,
      "age_text": "2003年8月",
      "image_url": "https://img01.suumo.com/jj/resizeImage?src=gazo%2Fbukken%2F030%2FN010000%2Fimg%2F069%2F20949069%2F20949069_0017.jpg&w=192&h=144",
      "address": "神奈川県茅ヶ崎市東海岸北３",
      "access": "ＪＲ東海道本線「茅ケ崎」徒歩11分"
    },
    {
      "source": "SUUMO",
      "type": "中古一戸建て",
      "name": "",
      "detail_url": "https://suumo.jp/chukoikkodate/tokyo/sc_suginami/nc_20576937/",
      "price": 3580.0,
      "price_text": "3580万円",
      "area": 68.03,
      "area_text": "68.03m2（20.57坪）（登記）、うち地下室21.66m2",
      "walk_minutes": 20,
      "walk_text": "阿佐ヶ谷駅 徒歩20分",
      "station": "阿佐ヶ谷",
      "age_years": 37,
      "age_text": "1989年8月",
      "image_url": "https://img01.suumo.com/jj/resizeImage?src=gazo%2Fbukken%2F030%2FN010000%2Fimg%2F937%2F20576937%2F20576937_0015.jpg&w=192&h=144",
      "address": "東京都杉並区松ノ木１",
      "access": "東京メトロ丸ノ内線「南阿佐ケ谷」徒歩20分"
    },
    {
      "source": "SUUMO",
      "type": "中古一戸建て",
      "name": "",
      "detail_url": "https://suumo.jp/chukoikkodate/kanagawa/sc_fujisawa/nc_20770757/",
      "price": 3190.0,
      "price_text": "3190万円",
      "area": 81.14,
      "area_text": "81.14m2",
      "walk_minutes": 12,
      "walk_text": "江ノ島駅 徒歩12分",
      "station": "江ノ島",
      "age_years": 19,
      "age_text": "2007年6月",
      "image_url": "https://img01.suumo.com/jj/resizeImage?src=gazo%2Fbukken%2F030%2FN010000%2Fimg%2F757%2F20770757%2F20770757_0019.jpg&w=192&h=144",
      "address": "神奈川県藤沢市善行５",
      "access": "小田急江ノ島線「善行」徒歩12分"
    },
    {
      "source": "SUUMO",
      "type": "中古一戸建て",
      "name": "藤沢市善行5丁目",
      "detail_url": "https://suumo.jp/chukoikkodate/kanagawa/sc_fujisawa/nc_20732133/",
      "price": 3190.0,
      "price_text": "3190万円",
      "area": 81.14,
      "area_text": "81.14m2（登記）",
      "walk_minutes": 13,
      "walk_text": "江ノ島駅 徒歩13分",
      "station": "江ノ島",
      "age_years": 19,
      "age_text": "2007年6月",
      "image_url": "https://img01.suumo.com/jj/resizeImage?src=gazo%2Fbukken%2F030%2FN010000%2Fimg%2F133%2F20732133%2F20732133_0003.jpg&w=192&h=144",
      "address": "神奈川県藤沢市善行５",
      "access": "小田急江ノ島線「善行」徒歩13分"
    },
    {
      "source": "SUUMO",
      "type": "中古一戸建て",
      "name": "神奈川県藤沢市稲荷１丁目",
      "detail_url": "https://suumo.jp/chukoikkodate/kanagawa/sc_fujisawa/nc_21087483/",
      "price": 3480.0,
      "price_text": "3480万円",
      "area": 101.74,
      "area_text": "101.74m2（30.77坪）（登記）",
      "walk_minutes": 19,
      "walk_text": "江ノ島駅 徒歩19分",
      "station": "江ノ島",
      "age_years": 19,
      "age_text": "2007年5月",
      "image_url": "https://img01.suumo.com/jj/resizeImage?src=gazo%2Fbukken%2F030%2FN010000%2Fimg%2F483%2F21087483%2F21087483_0001.jpg&w=192&h=144",
      "address": "神奈川県藤沢市稲荷１",
      "access": "小田急江ノ島線「藤沢本町」徒歩19分"
    },
    {
      "source": "SUUMO",
      "type": "中古一戸建て",
      "name": "",
      "detail_url": "https://suumo.jp/chukoikkodate/kanagawa/sc_fujisawa/nc_21139537/",
      "price": 3680.0,
      "price_text": "3680万円",
      "area": 98.82,
      "area_text": "98.82m2（29.89坪）",
      "walk_minutes": 15,
      "walk_text": "江ノ島駅 徒歩15分",
      "station": "江ノ島",
      "age_years": 15,
      "age_text": "2011年2月",
      "image_url": "https://img01.suumo.com/jj/resizeImage?src=gazo%2Fbukken%2F030%2FN010000%2Fimg%2F537%2F21139537%2F21139537_0033.jpg&w=192&h=144",
      "address": "神奈川県藤沢市稲荷１",
      "access": "小田急江ノ島線「藤沢本町」徒歩15分"
    },
    {
      "source": "SUUMO",
      "type": "中古一戸建て",
      "name": "",
      "detail_url": "https://suumo.jp/chukoikkodate/kanagawa/sc_fujisawa/nc_20699913/",
      "price": 3700.0,
      "price_text": "3700万円",
      "area": 70.38,
      "area_text": "70.38m2（21.28坪）（登記）",
      "walk_minutes": 20,
      "walk_text": "江ノ島駅 徒歩20分",
      "station": "江ノ島",
      "age_years": 10,
      "age_text": "2016年8月",
      "image_url": "https://img01.suumo.com/jj/resizeImage?src=gazo%2Fbukken%2F030%2FN010000%2Fimg%2F913%2F20699913%2F20699913_0019.jpg&w=192&h=144",
      "address": "神奈川県藤沢市辻堂東海岸３",
      "access": "小田急江ノ島線「鵠沼海岸」徒歩20分"
    },
    {
      "source": "SUUMO",
      "type": "中古一戸建て",
      "name": "陽当たりの良い南西道路に面した４ＬＤＫ戸建登場！！",
      "detail_url": "https://suumo.jp/chukoikkodate/kanagawa/sc_fujisawa/nc_78520446/",
      "price": 3730.0,
      "price_text": "3730万円",
      "area": 82.39,
      "area_text": "82.39m2（24.92坪）（登記）",
      "walk_minutes": 18,
      "walk_text": "江ノ島駅 徒歩18分",
      "station": "江ノ島",
      "age_years": 23,
      "age_text": "2003年7月",
      "image_url": "https://img01.suumo.com/jj/resizeImage?src=gazo%2Fbukken%2F030%2FN010000%2Fimg%2F446%2F78520446%2F78520446_0041.jpg&w=192&h=144",
      "address": "神奈川県藤沢市辻堂東海岸２",
      "access": "小田急江ノ島線「鵠沼海岸」徒歩18分"
    },
    {
      "source": "SUUMO",
      "type": "中古一戸建て",
      "name": "藤沢市高倉",
      "detail_url": "https://suumo.jp/chukoikkodate/kanagawa/sc_fujisawa/nc_20714408/",
      "price": 3797.0,
      "price_text": "3797万円",
      "area": 83.58,
      "area_text": "83.58m2",
      "walk_minutes": 12,
      "walk_text": "江ノ島駅 徒歩12分",
      "station": "江ノ島",
      "age_years": 31,
      "age_text": "1995年1月",
      "image_url": "https://img01.suumo.com/jj/resizeImage?src=gazo%2Fbukken%2F030%2FN010000%2Fimg%2F408%2F20714408%2F20714408_0015.jpg&w=192&h=144",
      "address": "神奈川県藤沢市高倉",
      "access": "小田急江ノ島線「長後」徒歩12分"
    },
    {
      "source": "SUUMO",
      "type": "中古一戸建て",
      "name": "藤沢市白旗2丁目　中古戸建",
      "detail_url": "https://suumo.jp/chukoikkodate/kanagawa/sc_fujisawa/nc_20392305/",
      "price": 4480.0,
      "price_text": "4480万円",
      "area": 124.9,
      "area_text": "124.9㎡（37.78坪）（登記）、うち１階車庫19.88...",
      "walk_minutes": 14,
      "walk_text": "江ノ島駅 徒歩14分",
      "station": "江ノ島",
      "age_years": 19,
      "age_text": "2007年11月",
      "image_url": "https://img01.suumo.com/jj/resizeImage?src=gazo%2Fbukken%2F030%2FN010000%2Fimg%2F305%2F20392305%2F20392305_0043.jpg&w=192&h=144",
      "address": "神奈川県藤沢市白旗２",
      "access": "小田急江ノ島線「藤沢本町」徒歩14分"
    },
    {
      "source": "SUUMO",
      "type": "中古一戸建て",
      "name": "敷地面積８８．４６坪。JR横須賀線「北鎌倉」駅徒歩９…",
      "detail_url": "https://suumo.jp/chukoikkodate/kanagawa/sc_kamakura/nc_72168930/",
      "price": 3000.0,
      "price_text": "3000万円",
      "area": 99.16,
      "area_text": "99.16m2（29.99坪）（登記）",
      "walk_minutes": 6,
      "walk_text": "鎌倉駅 徒歩6分",
      "station": "鎌倉",
      "age_years": 62,
      "age_text": "1964年1月",
      "image_url": "https://img01.suumo.com/jj/resizeImage?src=gazo%2Fbukken%2F030%2FN010000%2Fimg%2F930%2F72168930%2F72168930_0002.jpg&w=192&h=144",
      "address": "神奈川県鎌倉市山ノ内",
      "access": "ＪＲ横須賀線「北鎌倉」徒歩6分"
    },
    {
      "source": "SUUMO",
      "type": "中古一戸建て",
      "name": "",
      "detail_url": "https://suumo.jp/chukoikkodate/kanagawa/sc_kamakura/nc_77465233/",
      "price": 3999.0,
      "price_text": "3999万円",
      "area": 118.41,
      "area_text": "118.41m2（35.81坪）",
      "walk_minutes": 20,
      "walk_text": "江ノ島駅 徒歩20分",
      "station": "江ノ島",
      "age_years": 41,
      "age_text": "1985年3月",
      "image_url": "https://img01.suumo.com/jj/resizeImage?src=gazo%2Fbukken%2F030%2FN010000%2Fimg%2F233%2F77465233%2F77465233_0020.jpg&w=192&h=144",
      "address": "神奈川県鎌倉市笛田６",
      "access": "江ノ島電鉄線「長谷」徒歩20分"
    },
    {
      "source": "SUUMO",
      "type": "中古一戸建て",
      "name": "",
      "detail_url": "https://suumo.jp/chukoikkodate/kanagawa/sc_kamakura/nc_76761542/",
      "price": 3999.0,
      "price_text": "3999万円",
      "area": 118.41,
      "area_text": "118.41m2",
      "walk_minutes": 20,
      "walk_text": "江ノ島駅 徒歩20分",
      "station": "江ノ島",
      "age_years": 41,
      "age_text": "1985年3月",
      "image_url": "https://img01.suumo.com/jj/resizeImage?src=gazo%2Fbukken%2F030%2FN010000%2Fimg%2F542%2F76761542%2F76761542_0043.jpg&w=192&h=144",
      "address": "神奈川県鎌倉市笛田６",
      "access": "江ノ島電鉄線「長谷」徒歩20分"
    },
    {
      "source": "SUUMO",
      "type": "中古一戸建て",
      "name": "鎌倉市笛田6丁目　中古戸建",
      "detail_url": "https://suumo.jp/chukoikkodate/kanagawa/sc_kamakura/nc_79144475/",
      "price": 3999.0,
      "price_text": "3999万円",
      "area": 118.41,
      "area_text": "118.41m2（35.81坪）（登記）",
      "walk_minutes": 20,
      "walk_text": "江ノ島駅 徒歩20分",
      "station": "江ノ島",
      "age_years": 41,
      "age_text": "1985年3月",
      "image_url": "https://img01.suumo.com/jj/resizeImage?src=gazo%2Fbukken%2F030%2FN010000%2Fimg%2F475%2F79144475%2F79144475_0001.jpg&w=192&h=144",
      "address": "神奈川県鎌倉市笛田６",
      "access": "江ノ島電鉄線「長谷」徒歩20分"
    },
    {
      "source": "SUUMO",
      "type": "中古一戸建て",
      "name": "",
      "detail_url": "https://suumo.jp/chukoikkodate/kanagawa/sc_kamakura/nc_78810496/",
      "price": 3999.0,
      "price_text": "3999万円",
      "area": 118.41,
      "area_text": "118.41m2（登記）",
      "walk_minutes": 20,
      "walk_text": "江ノ島駅 徒歩20分",
      "station": "江ノ島",
      "age_years": 41,
      "age_text": "1985年3月",
      "image_url": "https://img01.suumo.com/jj/resizeImage?src=gazo%2Fbukken%2F030%2FN010000%2Fimg%2F496%2F78810496%2F78810496_0001.jpg&w=192&h=144",
      "address": "神奈川県鎌倉市笛田６",
      "access": "江ノ島電鉄線「極楽寺」徒歩20分"
    },
    {
      "source": "SUUMO",
      "type": "中古一戸建て",
      "name": "",
      "detail_url": "https://suumo.jp/chukoikkodate/kanagawa/sc_kamakura/nc_20893257/",
      "price": 4280.0,
      "price_text": "4280万円",
      "area": 111.74,
      "area_text": "111.74m2（登記）",
      "walk_minutes": 16,
      "walk_text": "江ノ島駅 徒歩16分",
      "station": "江ノ島",
      "age_years": 53,
      "age_text": "1973年8月",
      "image_url": "https://img01.suumo.com/jj/resizeImage?src=gazo%2Fbukken%2F030%2FN010000%2Fimg%2F257%2F20893257%2F20893257_0001.jpg&w=192&h=144",
      "address": "神奈川県鎌倉市笛田５",
      "access": "江ノ島電鉄線「極楽寺」徒歩16分"
    },
    {
      "source": "SUUMO",
      "type": "中古一戸建て",
      "name": "リフォーム済×築8年×室内美邸♪×鎌倉市手広2丁目【…",
      "detail_url": "https://suumo.jp/chukoikkodate/kanagawa/sc_kamakura/nc_20737822/",
      "price": 4397.0,
      "price_text": "4397万円",
      "area": 85.85,
      "area_text": "85.85m2（25.96坪）",
      "walk_minutes": 15,
      "walk_text": "鎌倉駅 徒歩15分",
      "station": "鎌倉",
      "age_years": 9,
      "age_text": "2017年11月",
      "image_url": "https://img01.suumo.com/jj/resizeImage?src=gazo%2Fbukken%2F030%2FN010000%2Fimg%2F822%2F20737822%2F20737822_0023.jpg&w=192&h=144",
      "address": "神奈川県鎌倉市手広２",
      "access": "湘南モノレール「西鎌倉」徒歩15分"
    },
    {
      "source": "SUUMO",
      "type": "中古一戸建て",
      "name": "◇◆鎌倉市手広２丁目　中古戸建◆◇",
      "detail_url": "https://suumo.jp/chukoikkodate/kanagawa/sc_kamakura/nc_20640423/",
      "price": 4397.0,
      "price_text": "4397万円",
      "area": 85.85,
      "area_text": "85.85m2（25.96坪）",
      "walk_minutes": 15,
      "walk_text": "鎌倉駅 徒歩15分",
      "station": "鎌倉",
      "age_years": 9,
      "age_text": "2017年11月",
      "image_url": "https://img01.suumo.com/jj/resizeImage?src=gazo%2Fbukken%2F030%2FN010000%2Fimg%2F423%2F20640423%2F20640423_0057.jpg&w=192&h=144",
      "address": "神奈川県鎌倉市手広２-31-10",
      "access": "湘南モノレール「西鎌倉」徒歩15分"
    },
    {
      "source": "SUUMO",
      "type": "中古一戸建て",
      "name": "【鎌倉市手広2丁目】",
      "detail_url": "https://suumo.jp/chukoikkodate/kanagawa/sc_kamakura/nc_20676500/",
      "price": 4397.0,
      "price_text": "4397万円",
      "area": 85.85,
      "area_text": "85.85m2（登記）",
      "walk_minutes": 12,
      "walk_text": "鎌倉駅 徒歩12分",
      "station": "鎌倉",
      "age_years": 9,
      "age_text": "2017年11月",
      "image_url": "https://img01.suumo.com/jj/resizeImage?src=gazo%2Fbukken%2F030%2FN010000%2Fimg%2F500%2F20676500%2F20676500_0087.jpg&w=192&h=144",
      "address": "神奈川県鎌倉市手広２",
      "access": "湘南モノレール「西鎌倉」徒歩12分"
    },
    {
      "source": "SUUMO",
      "type": "中古一戸建て",
      "name": "鎌倉市手広2丁目　中古戸建て",
      "detail_url": "https://suumo.jp/chukoikkodate/kanagawa/sc_kamakura/nc_20327554/",
      "price": 4497.0,
      "price_text": "4497万円",
      "area": 85.85,
      "area_text": "85.85m2（登記）",
      "walk_minutes": 14,
      "walk_text": "鎌倉駅 徒歩14分",
      "station": "鎌倉",
      "age_years": 9,
      "age_text": "2017年11月",
      "image_url": "https://img01.suumo.com/jj/resizeImage?src=gazo%2Fbukken%2F030%2FN010000%2Fimg%2F554%2F20327554%2F20327554_0043.jpg&w=192&h=144",
      "address": "神奈川県鎌倉市手広２",
      "access": "湘南モノレール「西鎌倉」徒歩14分"
    },
    {
      "source": "SUUMO",
      "type": "中古一戸建て",
      "name": "鎌倉市手広2丁目　中古戸建",
      "detail_url": "https://suumo.jp/chukoikkodate/kanagawa/sc_kamakura/nc_21067737/",
      "price": 4497.0,
      "price_text": "4497万円",
      "area": 85.85,
      "area_text": "85.85m2（25.96坪）（登記）",
      "walk_minutes": 15,
      "walk_text": "鎌倉駅 徒歩15分",
      "station": "鎌倉",
      "age_years": 9,
      "age_text": "2017年11月",
      "image_url": "https://img01.suumo.com/jj/resizeImage?src=gazo%2Fbukken%2F030%2FN010000%2Fimg%2F737%2F21067737%2F21067737_0001.jpg&w=192&h=144",
      "address": "神奈川県鎌倉市手広２",
      "access": "湘南モノレール「西鎌倉」徒歩15分"
    },
    {
      "source": "SUUMO",
      "type": "中古一戸建て",
      "name": "☆落ち着いた住環境が魅力☆茅ヶ崎市高田戸建",
      "detail_url": "https://suumo.jp/chukoikkodate/kanagawa/sc_chigasaki/nc_78194710/",
      "price": 2580.0,
      "price_text": "2580万円",
      "area": 77.17,
      "area_text": "77.17m2（登記）",
      "walk_minutes": 3,
      "walk_text": "茅ヶ崎駅",
      "station": "茅ヶ崎",
      "age_years": 19,
      "age_text": "2007年4月",
      "image_url": "https://img01.suumo.com/jj/resizeImage?src=gazo%2Fbukken%2F030%2FN010000%2Fimg%2F710%2F78194710%2F78194710_0082.jpg&w=192&h=144",
      "address": "神奈川県茅ヶ崎市高田４",
      "access": "ＪＲ東海道本線「茅ケ崎」バス9分停歩3分"
    },
    {
      "source": "SUUMO",
      "type": "中古一戸建て",
      "name": "海近と生活利便性が交わる立地。コストパフォーマンスの…",
      "detail_url": "https://suumo.jp/chukoikkodate/kanagawa/sc_chigasaki/nc_20957096/",
      "price": 2999.0,
      "price_text": "2999万円",
      "area": 69.34,
      "area_text": "69.34m2（登記）",
      "walk_minutes": 5,
      "walk_text": "茅ヶ崎駅",
      "station": "茅ヶ崎",
      "age_years": 26,
      "age_text": "2000年10月",
      "image_url": "https://img01.suumo.com/jj/resizeImage?src=gazo%2Fbukken%2F030%2FN010000%2Fimg%2F096%2F20957096%2F20957096_0001.jpg&w=192&h=144",
      "address": "神奈川県茅ヶ崎市南湖６",
      "access": "ＪＲ東海道本線「茅ケ崎」バス7分停歩5分"
    },
    {
      "source": "SUUMO",
      "type": "中古一戸建て",
      "name": "【売主】茅ヶ崎市中島４期　イーカム施工築浅中古戸建住…",
      "detail_url": "https://suumo.jp/chukoikkodate/kanagawa/sc_chigasaki/nc_20893978/",
      "price": 3180.0,
      "price_text": "3180万円",
      "area": 89.94,
      "area_text": "89.94m2",
      "walk_minutes": 5,
      "walk_text": "茅ヶ崎駅",
      "station": "茅ヶ崎",
      "age_years": 2,
      "age_text": "2024年6月",
      "image_url": "https://img01.suumo.com/jj/resizeImage?src=gazo%2Fbukken%2F030%2FN010000%2Fimg%2F978%2F20893978%2F20893978_2054.jpg&w=192&h=144",
      "address": "神奈川県茅ヶ崎市中島",
      "access": "ＪＲ東海道本線「茅ケ崎」バス8分停歩5分"
    },
    {
      "source": "SUUMO",
      "type": "中古一戸建て",
      "name": "【緑の潤いと静寂に包まれる暮らし。光と風が抜ける家】…",
      "detail_url": "https://suumo.jp/chukoikkodate/kanagawa/sc_chigasaki/nc_20735865/",
      "price": 3280.0,
      "price_text": "3280万円",
      "area": 99.36,
      "area_text": "99.36m2（30.05坪）（登記）",
      "walk_minutes": 1,
      "walk_text": "茅ヶ崎駅",
      "station": "茅ヶ崎",
      "age_years": 26,
      "age_text": "2000年11月",
      "image_url": "https://img01.suumo.com/jj/resizeImage?src=gazo%2Fbukken%2F030%2FN010000%2Fimg%2F865%2F20735865%2F20735865_0036.jpg&w=192&h=144",
      "address": "神奈川県茅ヶ崎市松林２",
      "access": "ＪＲ東海道本線「茅ケ崎」バス16分停歩1分"
    },
    {
      "source": "SUUMO",
      "type": "中古一戸建て",
      "name": "茅ヶ崎市茅ヶ崎戸建",
      "detail_url": "https://suumo.jp/chukoikkodate/kanagawa/sc_chigasaki/nc_78393172/",
      "price": 3580.0,
      "price_text": "3580万円",
      "area": 86.94,
      "area_text": "86.94m2（登記）",
      "walk_minutes": 5,
      "walk_text": "茅ヶ崎駅 徒歩5分",
      "station": "茅ヶ崎",
      "age_years": 19,
      "age_text": "2007年4月",
      "image_url": "https://img01.suumo.com/jj/resizeImage?src=gazo%2Fbukken%2F030%2FN010000%2Fimg%2F172%2F78393172%2F78393172_0003.jpg&w=192&h=144",
      "address": "神奈川県茅ヶ崎市茅ヶ崎",
      "access": "ＪＲ相模線「北茅ケ崎」徒歩5分"
    },
    {
      "source": "SUUMO",
      "type": "中古一戸建て",
      "name": "茅ヶ崎萩園トヨタホーム設計施工の注文住宅",
      "detail_url": "https://suumo.jp/chukoikkodate/kanagawa/sc_chigasaki/nc_20453735/",
      "price": 3878.0,
      "price_text": "3878万円",
      "area": 81.29,
      "area_text": "81.29m2",
      "walk_minutes": 10,
      "walk_text": "茅ヶ崎駅",
      "station": "茅ヶ崎",
      "age_years": 11,
      "age_text": "2015年3月",
      "image_url": "https://img01.suumo.com/jj/resizeImage?src=gazo%2Fbukken%2F030%2FN010000%2Fimg%2F735%2F20453735%2F20453735_0459.jpg&w=192&h=144",
      "address": "神奈川県茅ヶ崎市萩園",
      "access": "ＪＲ東海道本線「茅ケ崎」バス15分停歩10分"
    },
    {
      "source": "SUUMO",
      "type": "中古一戸建て",
      "name": "オープンセレクション茅ヶ崎",
      "detail_url": "https://suumo.jp/chukoikkodate/kanagawa/sc_chigasaki/nc_77679410/",
      "price": 3980.0,
      "price_text": "3980万円",
      "area": 82.18,
      "area_text": "82.18m2",
      "walk_minutes": 18,
      "walk_text": "茅ヶ崎駅 徒歩18分",
      "station": "茅ヶ崎",
      "age_years": 4,
      "age_text": "2022年11月",
      "image_url": "https://img01.suumo.com/jj/resizeImage?src=gazo%2Fbukken%2F030%2FN010000%2Fimg%2F410%2F77679410%2F77679410_0001.jpg&w=192&h=144",
      "address": "神奈川県茅ヶ崎市本村２",
      "access": "ＪＲ東海道本線「茅ケ崎」徒歩18分"
    },
    {
      "source": "SUUMO",
      "type": "中古一戸建て",
      "name": "オープンセレクション茅ケ崎",
      "detail_url": "https://suumo.jp/chukoikkodate/kanagawa/sc_chigasaki/nc_78698949/",
      "price": 4380.0,
      "price_text": "4380万円",
      "area": 87.25,
      "area_text": "87.25m2",
      "walk_minutes": 9,
      "walk_text": "茅ヶ崎駅 徒歩9分",
      "station": "茅ヶ崎",
      "age_years": 3,
      "age_text": "2023年11月",
      "image_url": "https://img01.suumo.com/jj/resizeImage?src=gazo%2Fbukken%2F030%2FN010000%2Fimg%2F949%2F78698949%2F78698949_0015.jpg&w=192&h=144",
      "address": "神奈川県茅ヶ崎市共恵１",
      "access": "湘南新宿ライン高海「茅ケ崎」徒歩9分"
    }
  ]
}