{
  "crawled_at": "2026-04-18T21:28:39.296831",
  "profile": "mercury",
  "conditions": {
    "stations": [
      "代々木",
      "代々木上原",
      "代々木公園",
      "信濃町",
      "内藤町",
      "千駄ヶ谷",
      "吉祥寺",
      "吉祥寺南町",
      "四ツ谷",
      "四谷",
      "大京町",
      "市谷",
      "御殿山",
      "明治神宮前",
      "渋谷",
      "表参道"
    ],
    "min_area_sqm": 40,
    "max_age_years": 20,
    "max_rent_man": 25.0
  },
  "summary": {
    "rental_count": 4,
    "new_count": 16,
    "used_count": 44,
    "suumo_rental": 3,
    "suumo_new": 16,
    "suumo_used": 39,
    "suumo_used_ikkodate": 0,
    "homes_rental": 1,
    "homes_new": 0,
    "homes_used": 0,
    "cowcamo_used": 5
  },
  "station_stats": {
    "rental": {
      "千駄ヶ谷": {
        "count": 2,
        "avg_price": 22.35,
        "median_price": 22.35,
        "min_price": 19.9,
        "max_price": 24.8,
        "avg_price_per_sqm": 0.4423,
        "median_price_per_sqm": 0.4423,
        "p25_price_per_sqm": 0.3938,
        "p75_price_per_sqm": 0.4908,
        "avg_area": 50.53,
        "avg_age": 19,
        "avg_walk": 8,
        "new_listings": 0,
        "delisted": 0,
        "price_reduced": 0,
        "stale_count": 0
      },
      "内藤町": {
        "count": 1,
        "avg_price": 22.9,
        "median_price": 22.9,
        "min_price": 22.9,
        "max_price": 22.9,
        "avg_price_per_sqm": 0.5195,
        "median_price_per_sqm": 0.5195,
        "p25_price_per_sqm": 0.5195,
        "p75_price_per_sqm": 0.5195,
        "avg_area": 44.08,
        "avg_age": 9,
        "avg_walk": 6,
        "new_listings": 0,
        "delisted": 2,
        "price_reduced": 0,
        "stale_count": 1
      },
      "吉祥寺": {
        "count": 1,
        "avg_price": 23.5,
        "median_price": 23.5,
        "min_price": 23.5,
        "max_price": 23.5,
        "avg_price_per_sqm": 0.5383,
        "median_price_per_sqm": 0.5383,
        "p25_price_per_sqm": 0.5383,
        "p75_price_per_sqm": 0.5383,
        "avg_area": 43.66,
        "avg_age": null,
        "avg_walk": 10,
        "new_listings": 0,
        "delisted": 0,
        "price_reduced": 0,
        "stale_count": 0
      }
    },
    "new": {
      "吉祥寺南町": {
        "count": 1,
        "avg_price": null,
        "median_price": null,
        "min_price": null,
        "max_price": null,
        "avg_price_per_sqm": null,
        "median_price_per_sqm": null,
        "p25_price_per_sqm": null,
        "p75_price_per_sqm": null,
        "avg_area": 84.38,
        "avg_age": 0,
        "avg_walk": 7,
        "new_listings": 0,
        "delisted": 0,
        "price_reduced": 0,
        "stale_count": 1
      },
      "吉祥寺": {
        "count": 4,
        "avg_price": 15466,
        "median_price": 15480,
        "min_price": 12438,
        "max_price": 18480,
        "avg_price_per_sqm": 247.2232,
        "median_price_per_sqm": 227.8668,
        "p25_price_per_sqm": 227.7188,
        "p75_price_per_sqm": 286.0839,
        "avg_area": 63.36,
        "avg_age": 0,
        "avg_walk": 7.5,
        "new_listings": 0,
        "delisted": 0,
        "price_reduced": 0,
        "stale_count": 4
      },
      "渋谷": {
        "count": 10,
        "avg_price": 22926,
        "median_price": 22900.0,
        "min_price": 22480,
        "max_price": 24000,
        "avg_price_per_sqm": 367.7664,
        "median_price_per_sqm": 374.7341,
        "p25_price_per_sqm": 366.1238,
        "p75_price_per_sqm": 374.7341,
        "avg_area": 62.504,
        "avg_age": 0,
        "avg_walk": 8.3,
        "new_listings": 0,
        "delisted": 0,
        "price_reduced": 0,
        "stale_count": 7
      },
      "四ツ谷": {
        "count": 1,
        "avg_price": null,
        "median_price": null,
        "min_price": null,
        "max_price": null,
        "avg_price_per_sqm": null,
        "median_price_per_sqm": null,
        "p25_price_per_sqm": null,
        "p75_price_per_sqm": null,
        "avg_area": 70.07,
        "avg_age": 0,
        "avg_walk": 3,
        "new_listings": 0,
        "delisted": 0,
        "price_reduced": 0,
        "stale_count": 1
      }
    },
    "used": {
      "吉祥寺": {
        "count": 7,
        "avg_price": 18437.1429,
        "median_price": 16200.0,
        "min_price": 11980,
        "max_price": 32500.0,
        "avg_price_per_sqm": 199.4867,
        "median_price_per_sqm": 197.5268,
        "p25_price_per_sqm": 167.9975,
        "p75_price_per_sqm": 256.8351,
        "avg_area": 102.3814,
        "avg_age": 6.3333,
        "avg_walk": 4.8571,
        "new_listings": 0,
        "delisted": 1,
        "price_reduced": 0,
        "stale_count": 3
      },
      "御殿山": {
        "count": 5,
        "avg_price": 18926,
        "median_price": 15980,
        "min_price": 12990,
        "max_price": 25980,
        "avg_price_per_sqm": 215.2487,
        "median_price_per_sqm": 213.9224,
        "p25_price_per_sqm": 207.5787,
        "p75_price_per_sqm": 231.2862,
        "avg_area": 86.508,
        "avg_age": 14.8,
        "avg_walk": 10.2,
        "new_listings": 0,
        "delisted": 0,
        "price_reduced": 0,
        "stale_count": 5
      },
      "千駄ヶ谷": {
        "count": 2,
        "avg_price": 43140,
        "median_price": 43140.0,
        "min_price": 16480,
        "max_price": 69800,
        "avg_price_per_sqm": 475.197,
        "median_price_per_sqm": 475.197,
        "p25_price_per_sqm": 387.309,
        "p75_price_per_sqm": 563.0849,
        "avg_area": 83.255,
        "avg_age": 4.5,
        "avg_walk": 3.5,
        "new_listings": 0,
        "delisted": 0,
        "price_reduced": 0,
        "stale_count": 2
      },
      "大京町": {
        "count": 10,
        "avg_price": 24726,
        "median_price": 23250.0,
        "min_price": 13500,
        "max_price": 55000,
        "avg_price_per_sqm": 293.6165,
        "median_price_per_sqm": 282.6424,
        "p25_price_per_sqm": 273.7237,
        "p75_price_per_sqm": 282.6424,
        "avg_area": 81.554,
        "avg_age": 11.3,
        "avg_walk": 7.2,
        "new_listings": 1,
        "delisted": 0,
        "price_reduced": 0,
        "stale_count": 8
      },
      "内藤町": {
        "count": 10,
        "avg_price": 28567,
        "median_price": 25490.0,
        "min_price": 13980,
        "max_price": 62800,
        "avg_price_per_sqm": 342.8882,
        "median_price_per_sqm": 322.3097,
        "p25_price_per_sqm": 298.8976,
        "p75_price_per_sqm": 384.6064,
        "avg_area": 79.493,
        "avg_age": 11.2,
        "avg_walk": 6.3,
        "new_listings": 0,
        "delisted": 0,
        "price_reduced": 0,
        "stale_count": 7
      },
      "四谷": {
        "count": 9,
        "avg_price": 31785.5556,
        "median_price": 29000,
        "min_price": 17600,
        "max_price": 63980,
        "avg_price_per_sqm": 391.3451,
        "median_price_per_sqm": 387.0796,
        "p25_price_per_sqm": 377.8115,
        "p75_price_per_sqm": 435.1088,
        "avg_area": 79.0722,
        "avg_age": 3.8889,
        "avg_walk": 4.3333,
        "new_listings": 0,
        "delisted": 0,
        "price_reduced": 0,
        "stale_count": 8
      },
      "代々木": {
        "count": 1,
        "avg_price": 24800.0,
        "median_price": 24800.0,
        "min_price": 24800.0,
        "max_price": 24800.0,
        "avg_price_per_sqm": 189.8492,
        "median_price_per_sqm": 189.8492,
        "p25_price_per_sqm": 189.8492,
        "p75_price_per_sqm": 189.8492,
        "avg_area": 130.63,
        "avg_age": null,
        "avg_walk": 5,
        "new_listings": 0,
        "delisted": 0,
        "price_reduced": 0,
        "stale_count": 0
      }
    }
  },
  "changes": {
    "price_reduced": [],
    "new_listings": [
      {
        "uid": "f62f2cd6b421",
        "name": "マジェスティハウス新宿御苑パークナード",
        "station": "大京町",
        "type": "used",
        "price": 25500,
        "detail_url": "https://suumo.jp/ms/chuko/tokyo/sc_shinjuku/nc_78868985/"
      }
    ],
    "delisted": [
      {
        "uid": "f8780b303fc5",
        "name": "プラウドタワー渋谷",
        "station": "表参道",
        "type": "new",
        "last_price": 29800,
        "detail_url": "https://suumo.jp/ms/shinchiku/tokyo/sc_shibuya/nc_78876127/",
        "first_seen": "2026-03-20",
        "last_seen": "2026-04-17"
      },
      {
        "uid": "d998cdf1b1d2",
        "name": "プライムアーバン新宿内藤町",
        "station": "内藤町",
        "type": "rental",
        "last_price": 18.5,
        "detail_url": "https://suumo.jp/chintai/jnc_000105300085/",
        "first_seen": "2026-04-02",
        "last_seen": "2026-04-18"
      },
      {
        "uid": "c7aa1ffe872c",
        "name": "プライムアーバン新宿内藤町",
        "station": "内藤町",
        "type": "rental",
        "last_price": 19.9,
        "detail_url": "https://suumo.jp/chintai/jnc_000106145859/",
        "first_seen": "2026-04-02",
        "last_seen": "2026-04-18"
      },
      {
        "uid": "8da49e4de24d",
        "name": "ファインスクェア吉祥寺ザ・プレミアム",
        "station": "吉祥寺",
        "type": "used",
        "last_price": 17500,
        "detail_url": "https://suumo.jp/ms/chuko/tokyo/sc_musashino/nc_20636379/",
        "first_seen": "2026-04-11",
        "last_seen": "2026-04-17"
      },
      {
        "uid": "f901771abe4c",
        "name": "イプセ代々木上原Residence",
        "station": "代々木",
        "type": "rental",
        "last_price": 21.0,
        "detail_url": "https://www.homes.co.jp/chintai/room/b69aea9c8e61a3a52e8957f0a2ac7035677401cc/",
        "first_seen": "2026-04-16",
        "last_seen": "2026-04-18"
      }
    ],
    "stale": [
      {
        "uid": "1906d1bf5d5a",
        "name": "サンクレイドル御苑内藤町",
        "station": "内藤町",
        "type": "rental",
        "days_listed": 19,
        "price": 22.9,
        "detail_url": "https://suumo.jp/chintai/jnc_000104752936/"
      },
      {
        "uid": "cdce3619e703",
        "name": "リビオ吉祥寺南町",
        "station": "吉祥寺南町",
        "type": "new",
        "days_listed": 29,
        "price": null,
        "detail_url": "https://suumo.jp/ms/shinchiku/tokyo/sc_musashino/nc_67729878/"
      },
      {
        "uid": "eab96d2bb535",
        "name": "プラウド吉祥寺本町",
        "station": "吉祥寺",
        "type": "new",
        "days_listed": 29,
        "price": 12438,
        "detail_url": "https://suumo.jp/ms/shinchiku/tokyo/sc_musashino/nc_67730928/"
      },
      {
        "uid": "88ecddff786c",
        "name": "ザ・パークハウス 吉祥寺プレイス",
        "station": "吉祥寺",
        "type": "new",
        "days_listed": 29,
        "price": null,
        "detail_url": "https://suumo.jp/ms/shinchiku/tokyo/sc_musashino/nc_67729222/"
      },
      {
        "uid": "63e0514ed451",
        "name": "サンウッド吉祥寺南町一丁目",
        "station": "吉祥寺",
        "type": "new",
        "days_listed": 29,
        "price": 15480,
        "detail_url": "https://suumo.jp/ms/shinchiku/tokyo/sc_musashino/nc_20315710/"
      },
      {
        "uid": "7badd8c6a9d9",
        "name": "オープンレジデンシア吉祥寺本町テラス",
        "station": "吉祥寺",
        "type": "new",
        "days_listed": 14,
        "price": 18480,
        "detail_url": "https://suumo.jp/ms/shinchiku/tokyo/sc_musashino/nc_78674441/"
      },
      {
        "uid": "4ae94cfcb5f9",
        "name": "プラウドタワー渋谷",
        "station": "渋谷",
        "type": "new",
        "days_listed": 29,
        "price": 22480,
        "detail_url": "https://suumo.jp/ms/shinchiku/tokyo/sc_shibuya/nc_79020596/"
      },
      {
        "uid": "ac9573d3c321",
        "name": "プラウドタワー渋谷",
        "station": "渋谷",
        "type": "new",
        "days_listed": 29,
        "price": 22480,
        "detail_url": "https://suumo.jp/ms/shinchiku/tokyo/sc_shibuya/nc_78961344/"
      },
      {
        "uid": "6f3f2d7ef79b",
        "name": "プラウド渋谷東",
        "station": "渋谷",
        "type": "new",
        "days_listed": 18,
        "price": 22900,
        "detail_url": "https://suumo.jp/ms/shinchiku/tokyo/sc_shibuya/nc_20559804/"
      },
      {
        "uid": "cde9bdb8b05f",
        "name": "プラウド渋谷東",
        "station": "渋谷",
        "type": "new",
        "days_listed": 29,
        "price": 22900,
        "detail_url": "https://suumo.jp/ms/shinchiku/tokyo/sc_shibuya/nc_20246272/"
      },
      {
        "uid": "d394d1b3b16b",
        "name": "プラウド渋谷東",
        "station": "渋谷",
        "type": "new",
        "days_listed": 29,
        "price": 22900,
        "detail_url": "https://suumo.jp/ms/shinchiku/tokyo/sc_shibuya/nc_20152029/"
      },
      {
        "uid": "beb27de9fe0c",
        "name": "プラウド渋谷東",
        "station": "渋谷",
        "type": "new",
        "days_listed": 29,
        "price": 22900,
        "detail_url": "https://suumo.jp/ms/shinchiku/tokyo/sc_shibuya/nc_20145319/"
      },
      {
        "uid": "e7ee3e959319",
        "name": "プラウド渋谷東",
        "station": "渋谷",
        "type": "new",
        "days_listed": 29,
        "price": 22900,
        "detail_url": "https://suumo.jp/ms/shinchiku/tokyo/sc_shibuya/nc_20094647/"
      },
      {
        "uid": "0ac89a954bbd",
        "name": "プラウド四谷",
        "station": "四ツ谷",
        "type": "new",
        "days_listed": 29,
        "price": null,
        "detail_url": "https://suumo.jp/ms/shinchiku/tokyo/sc_shinjuku/nc_67734365/"
      },
      {
        "uid": "2de6a14d2fbc",
        "name": "サンウッド吉祥寺南町一丁目",
        "station": "吉祥寺",
        "type": "used",
        "days_listed": 17,
        "price": 11980,
        "detail_url": "https://suumo.jp/ms/chuko/tokyo/sc_musashino/nc_20564565/"
      },
      {
        "uid": "dc55ced09c3b",
        "name": "ルジェンテ吉祥寺",
        "station": "吉祥寺",
        "type": "used",
        "days_listed": 19,
        "price": 11980,
        "detail_url": "https://suumo.jp/ms/chuko/tokyo/sc_musashino/nc_78280842/"
      },
      {
        "uid": "521c6e0117bc",
        "name": "井の頭公園パークハウス吉祥寺南町",
        "station": "吉祥寺",
        "type": "used",
        "days_listed": 19,
        "price": 24800,
        "detail_url": "https://suumo.jp/ms/chuko/tokyo/sc_musashino/nc_20394756/"
      },
      {
        "uid": "f8f1c123a4b5",
        "name": "プラネスーペリア御殿山井の頭公園",
        "station": "御殿山",
        "type": "used",
        "days_listed": 19,
        "price": 12990,
        "detail_url": "https://suumo.jp/ms/chuko/tokyo/sc_musashino/nc_78668650/"
      },
      {
        "uid": "7d9c092c2bde",
        "name": "プラネスーペリア御殿山　井の頭公園",
        "station": "御殿山",
        "type": "used",
        "days_listed": 19,
        "price": 14900,
        "detail_url": "https://suumo.jp/ms/chuko/tokyo/sc_musashino/nc_20503725/"
      },
      {
        "uid": "1bc1136311de",
        "name": "ルフォン井の頭公園",
        "station": "御殿山",
        "type": "used",
        "days_listed": 19,
        "price": 15980,
        "detail_url": "https://suumo.jp/ms/chuko/tokyo/sc_musashino/nc_20503722/"
      },
      {
        "uid": "a502d6ed7b35",
        "name": "ルフォン吉祥寺",
        "station": "御殿山",
        "type": "used",
        "days_listed": 19,
        "price": 24780,
        "detail_url": "https://suumo.jp/ms/chuko/tokyo/sc_musashino/nc_20390486/"
      },
      {
        "uid": "cf01ee77caef",
        "name": "ルフォン吉祥寺",
        "station": "御殿山",
        "type": "used",
        "days_listed": 19,
        "price": 25980,
        "detail_url": "https://suumo.jp/ms/chuko/tokyo/sc_musashino/nc_79071425/"
      },
      {
        "uid": "2fde0c74a763",
        "name": "パークコート神宮北参道　ザ　タワー",
        "station": "千駄ヶ谷",
        "type": "used",
        "days_listed": 29,
        "price": 16480,
        "detail_url": "https://suumo.jp/ms/chuko/tokyo/sc_shibuya/nc_20054220/"
      },
      {
        "uid": "da8d9ac94dd7",
        "name": "THE　KITA",
        "station": "千駄ヶ谷",
        "type": "used",
        "days_listed": 29,
        "price": 69800,
        "detail_url": "https://suumo.jp/ms/chuko/tokyo/sc_shibuya/nc_78063221/"
      },
      {
        "uid": "e3256d27c059",
        "name": "マジェスティハウス新宿御苑パークナード",
        "station": "大京町",
        "type": "used",
        "days_listed": 29,
        "price": 16980,
        "detail_url": "https://suumo.jp/ms/chuko/tokyo/sc_shinjuku/nc_79051221/"
      },
      {
        "uid": "4a2cd9d291fe",
        "name": "VECS♪マジェスティハウス新宿御苑パークナード",
        "station": "大京町",
        "type": "used",
        "days_listed": 29,
        "price": 25500,
        "detail_url": "https://suumo.jp/ms/chuko/tokyo/sc_shinjuku/nc_78727043/"
      },
      {
        "uid": "1846f2c7ee1e",
        "name": "マジェスティハウス新宿御苑パークナード",
        "station": "大京町",
        "type": "used",
        "days_listed": 29,
        "price": 13500,
        "detail_url": "https://suumo.jp/ms/chuko/tokyo/sc_shinjuku/nc_78681542/"
      },
      {
        "uid": "3631c2270712",
        "name": "プラウド新宿御苑エンパイア",
        "station": "大京町",
        "type": "used",
        "days_listed": 19,
        "price": 18980,
        "detail_url": "https://suumo.jp/ms/chuko/tokyo/sc_shinjuku/nc_20342635/"
      },
      {
        "uid": "f27b2cf06638",
        "name": "マジェスティハウス新宿御苑パークナード",
        "station": "大京町",
        "type": "used",
        "days_listed": 19,
        "price": 19800,
        "detail_url": "https://suumo.jp/ms/chuko/tokyo/sc_shinjuku/nc_20496669/"
      },
      {
        "uid": "4b5a59f658a8",
        "name": "マジェスティハウス新宿御苑パークナード",
        "station": "大京町",
        "type": "used",
        "days_listed": 18,
        "price": 21000,
        "detail_url": "https://suumo.jp/ms/chuko/tokyo/sc_shinjuku/nc_20417672/"
      },
      {
        "uid": "0fbfb1e98e59",
        "name": "マジェスティハウス新宿御苑パークナード",
        "station": "大京町",
        "type": "used",
        "days_listed": 19,
        "price": 25500,
        "detail_url": "https://suumo.jp/ms/chuko/tokyo/sc_shinjuku/nc_20153655/"
      },
      {
        "uid": "ea70a533193a",
        "name": "マジェスティハウス新宿御苑パークナード",
        "station": "大京町",
        "type": "used",
        "days_listed": 19,
        "price": 25500,
        "detail_url": "https://suumo.jp/ms/chuko/tokyo/sc_shinjuku/nc_78466132/"
      },
      {
        "uid": "357cf6335460",
        "name": "ジオ御苑内藤町",
        "station": "内藤町",
        "type": "used",
        "days_listed": 19,
        "price": 13980,
        "detail_url": "https://suumo.jp/ms/chuko/tokyo/sc_shinjuku/nc_20246769/"
      },
      {
        "uid": "603138d1f83a",
        "name": "ディアナコート御苑内藤町",
        "station": "内藤町",
        "type": "used",
        "days_listed": 19,
        "price": 18980,
        "detail_url": "https://suumo.jp/ms/chuko/tokyo/sc_shinjuku/nc_20212283/"
      },
      {
        "uid": "20b667a5897b",
        "name": "フォルム内藤町",
        "station": "内藤町",
        "type": "used",
        "days_listed": 29,
        "price": 35990,
        "detail_url": "https://suumo.jp/ms/chuko/tokyo/sc_shinjuku/nc_79134743/"
      },
      {
        "uid": "1a4d5c667192",
        "name": "ディアナコート御苑内藤町",
        "station": "内藤町",
        "type": "used",
        "days_listed": 19,
        "price": 18000,
        "detail_url": "https://suumo.jp/ms/chuko/tokyo/sc_shinjuku/nc_20186845/"
      },
      {
        "uid": "8ae6a9037086",
        "name": "ディアナコート御苑内藤町",
        "station": "内藤町",
        "type": "used",
        "days_listed": 18,
        "price": 18980,
        "detail_url": "https://suumo.jp/ms/chuko/tokyo/sc_shinjuku/nc_20186846/"
      },
      {
        "uid": "e912c156eb16",
        "name": "フォルム内藤町 新宿御苑前｜駅歩6分｜新規リノベーシ…",
        "station": "内藤町",
        "type": "used",
        "days_listed": 26,
        "price": 32980,
        "detail_url": "https://suumo.jp/ms/chuko/tokyo/sc_shinjuku/nc_20416827/"
      },
      {
        "uid": "4d957176c7bd",
        "name": "ジオ御苑内藤町",
        "station": "内藤町",
        "type": "used",
        "days_listed": 19,
        "price": 62800,
        "detail_url": "https://suumo.jp/ms/chuko/tokyo/sc_shinjuku/nc_20212271/"
      },
      {
        "uid": "f1b1f09581db",
        "name": "クラッシィタワー新宿御苑",
        "station": "四谷",
        "type": "used",
        "days_listed": 18,
        "price": 17600,
        "detail_url": "https://suumo.jp/ms/chuko/tokyo/sc_shinjuku/nc_20553154/"
      },
      {
        "uid": "c76e68996931",
        "name": "ライオンズ四谷タワーゲート",
        "station": "四谷",
        "type": "used",
        "days_listed": 19,
        "price": 19990,
        "detail_url": "https://suumo.jp/ms/chuko/tokyo/sc_shinjuku/nc_78586303/"
      },
      {
        "uid": "3e56aa18f40b",
        "name": "クラッシィタワー新宿御苑1905号室",
        "station": "四谷",
        "type": "used",
        "days_listed": 15,
        "price": 29900,
        "detail_url": "https://suumo.jp/ms/chuko/tokyo/sc_shinjuku/nc_20488546/"
      },
      {
        "uid": "a9dbe81bf659",
        "name": "クラッシィタワー新宿御苑",
        "station": "四谷",
        "type": "used",
        "days_listed": 29,
        "price": 32800,
        "detail_url": "https://suumo.jp/ms/chuko/tokyo/sc_shinjuku/nc_78725482/"
      },
      {
        "uid": "5d8cf9c4e248",
        "name": "クラッシィタワー新宿御苑",
        "station": "四谷",
        "type": "used",
        "days_listed": 19,
        "price": 34800,
        "detail_url": "https://suumo.jp/ms/chuko/tokyo/sc_shinjuku/nc_20347740/"
      },
      {
        "uid": "4dd469f990dd",
        "name": "クラッシィタワー新宿御苑",
        "station": "四谷",
        "type": "used",
        "days_listed": 29,
        "price": 29000,
        "detail_url": "https://suumo.jp/ms/chuko/tokyo/sc_shinjuku/nc_78790755/"
      },
      {
        "uid": "305b2b9cce93",
        "name": "クラッシィタワー新宿御苑",
        "station": "四谷",
        "type": "used",
        "days_listed": 29,
        "price": 29000,
        "detail_url": "https://suumo.jp/ms/chuko/tokyo/sc_shinjuku/nc_78937109/"
      },
      {
        "uid": "937b775f4931",
        "name": "クラッシィタワー新宿御苑",
        "station": "四谷",
        "type": "used",
        "days_listed": 29,
        "price": 63980,
        "detail_url": "https://suumo.jp/ms/chuko/tokyo/sc_shinjuku/nc_20333866/"
      }
    ],
    "station_summary": {
      "千駄ヶ谷": {
        "rental": {
          "new_count": 0,
          "delisted_count": 0,
          "price_reduced_count": 0,
          "stale_count": 0
        },
        "new": {
          "new_count": 0,
          "delisted_count": 0,
          "price_reduced_count": 0,
          "stale_count": 0
        },
        "used": {
          "new_count": 0,
          "delisted_count": 0,
          "price_reduced_count": 0,
          "stale_count": 2
        }
      },
      "内藤町": {
        "rental": {
          "new_count": 0,
          "delisted_count": 2,
          "price_reduced_count": 0,
          "stale_count": 1
        },
        "new": {
          "new_count": 0,
          "delisted_count": 0,
          "price_reduced_count": 0,
          "stale_count": 0
        },
        "used": {
          "new_count": 0,
          "delisted_count": 0,
          "price_reduced_count": 0,
          "stale_count": 7
        }
      },
      "代々木公園": {
        "rental": {
          "new_count": 0,
          "delisted_count": 0,
          "price_reduced_count": 0,
          "stale_count": 0
        },
        "new": {
          "new_count": 0,
          "delisted_count": 0,
          "price_reduced_count": 0,
          "stale_count": 0
        },
        "used": {
          "new_count": 0,
          "delisted_count": 0,
          "price_reduced_count": 0,
          "stale_count": 0
        }
      },
      "渋谷": {
        "rental": {
          "new_count": 0,
          "delisted_count": 0,
          "price_reduced_count": 0,
          "stale_count": 0
        },
        "new": {
          "new_count": 0,
          "delisted_count": 0,
          "price_reduced_count": 0,
          "stale_count": 7
        },
        "used": {
          "new_count": 0,
          "delisted_count": 0,
          "price_reduced_count": 0,
          "stale_count": 0
        }
      },
      "信濃町": {
        "rental": {
          "new_count": 0,
          "delisted_count": 0,
          "price_reduced_count": 0,
          "stale_count": 0
        },
        "new": {
          "new_count": 0,
          "delisted_count": 0,
          "price_reduced_count": 0,
          "stale_count": 0
        },
        "used": {
          "new_count": 0,
          "delisted_count": 0,
          "price_reduced_count": 0,
          "stale_count": 0
        }
      },
      "四ツ谷": {
        "rental": {
          "new_count": 0,
          "delisted_count": 0,
          "price_reduced_count": 0,
          "stale_count": 0
        },
        "new": {
          "new_count": 0,
          "delisted_count": 0,
          "price_reduced_count": 0,
          "stale_count": 1
        },
        "used": {
          "new_count": 0,
          "delisted_count": 0,
          "price_reduced_count": 0,
          "stale_count": 0
        }
      },
      "吉祥寺": {
        "rental": {
          "new_count": 0,
          "delisted_count": 0,
          "price_reduced_count": 0,
          "stale_count": 0
        },
        "new": {
          "new_count": 0,
          "delisted_count": 0,
          "price_reduced_count": 0,
          "stale_count": 4
        },
        "used": {
          "new_count": 0,
          "delisted_count": 1,
          "price_reduced_count": 0,
          "stale_count": 3
        }
      },
      "大京町": {
        "rental": {
          "new_count": 0,
          "delisted_count": 0,
          "price_reduced_count": 0,
          "stale_count": 0
        },
        "new": {
          "new_count": 0,
          "delisted_count": 0,
          "price_reduced_count": 0,
          "stale_count": 0
        },
        "used": {
          "new_count": 1,
          "delisted_count": 0,
          "price_reduced_count": 0,
          "stale_count": 8
        }
      },
      "吉祥寺南町": {
        "rental": {
          "new_count": 0,
          "delisted_count": 0,
          "price_reduced_count": 0,
          "stale_count": 0
        },
        "new": {
          "new_count": 0,
          "delisted_count": 0,
          "price_reduced_count": 0,
          "stale_count": 1
        },
        "used": {
          "new_count": 0,
          "delisted_count": 0,
          "price_reduced_count": 0,
          "stale_count": 0
        }
      },
      "代々木上原": {
        "rental": {
          "new_count": 0,
          "delisted_count": 0,
          "price_reduced_count": 0,
          "stale_count": 0
        },
        "new": {
          "new_count": 0,
          "delisted_count": 0,
          "price_reduced_count": 0,
          "stale_count": 0
        },
        "used": {
          "new_count": 0,
          "delisted_count": 0,
          "price_reduced_count": 0,
          "stale_count": 0
        }
      },
      "明治神宮前": {
        "rental": {
          "new_count": 0,
          "delisted_count": 0,
          "price_reduced_count": 0,
          "stale_count": 0
        },
        "new": {
          "new_count": 0,
          "delisted_count": 0,
          "price_reduced_count": 0,
          "stale_count": 0
        },
        "used": {
          "new_count": 0,
          "delisted_count": 0,
          "price_reduced_count": 0,
          "stale_count": 0
        }
      },
      "四谷": {
        "rental": {
          "new_count": 0,
          "delisted_count": 0,
          "price_reduced_count": 0,
          "stale_count": 0
        },
        "new": {
          "new_count": 0,
          "delisted_count": 0,
          "price_reduced_count": 0,
          "stale_count": 0
        },
        "used": {
          "new_count": 0,
          "delisted_count": 0,
          "price_reduced_count": 0,
          "stale_count": 8
        }
      },
      "御殿山": {
        "rental": {
          "new_count": 0,
          "delisted_count": 0,
          "price_reduced_count": 0,
          "stale_count": 0
        },
        "new": {
          "new_count": 0,
          "delisted_count": 0,
          "price_reduced_count": 0,
          "stale_count": 0
        },
        "used": {
          "new_count": 0,
          "delisted_count": 0,
          "price_reduced_count": 0,
          "stale_count": 5
        }
      },
      "市谷": {
        "rental": {
          "new_count": 0,
          "delisted_count": 0,
          "price_reduced_count": 0,
          "stale_count": 0
        },
        "new": {
          "new_count": 0,
          "delisted_count": 0,
          "price_reduced_count": 0,
          "stale_count": 0
        },
        "used": {
          "new_count": 0,
          "delisted_count": 0,
          "price_reduced_count": 0,
          "stale_count": 0
        }
      },
      "代々木": {
        "rental": {
          "new_count": 0,
          "delisted_count": 1,
          "price_reduced_count": 0,
          "stale_count": 0
        },
        "new": {
          "new_count": 0,
          "delisted_count": 0,
          "price_reduced_count": 0,
          "stale_count": 0
        },
        "used": {
          "new_count": 0,
          "delisted_count": 0,
          "price_reduced_count": 0,
          "stale_count": 0
        }
      },
      "表参道": {
        "rental": {
          "new_count": 0,
          "delisted_count": 0,
          "price_reduced_count": 0,
          "stale_count": 0
        },
        "new": {
          "new_count": 0,
          "delisted_count": 1,
          "price_reduced_count": 0,
          "stale_count": 0
        },
        "used": {
          "new_count": 0,
          "delisted_count": 0,
          "price_reduced_count": 0,
          "stale_count": 0
        }
      }
    },
    "summary": {
      "total_new": 1,
      "total_delisted": 5,
      "total_price_reduced": 0,
      "total_stale": 47
    }
  },
  "rental": [
    {
      "source": "SUUMO",
      "type": "賃貸",
      "name": "ガーデンクレスト",
      "detail_url": "https://suumo.jp/chintai/jnc_000106472501/",
      "price": 19.9,
      "price_text": "19.9万円10000円",
      "management_fee": 19.9,
      "management_fee_text": "19.9万円19.9万円",
      "area": 50.53,
      "area_text": "50.53m²",
      "walk_minutes": 8,
      "walk_text": "千駄ヶ谷駅",
      "station": "千駄ヶ谷",
      "age_years": 19,
      "age_text": "築19年",
      "image_url": "https://img01.suumo.com/front/gazo/fr/bukken/025/100501277025/100501277025_go.jpg",
      "address": "東京都新宿区大京町",
      "access": "東京メトロ丸ノ内線/四谷三丁目駅 歩7分 / 東京メトロ丸ノ内線/新宿御苑前駅 歩8分 / ＪＲ中央線/千駄ケ谷駅 歩8分"
    },
    {
      "source": "SUUMO",
      "type": "賃貸",
      "name": "ガーデンクレスト",
      "detail_url": "https://suumo.jp/chintai/jnc_000103316446/",
      "price": 24.8,
      "price_text": "24.8万円10000円",
      "management_fee": 24.8,
      "management_fee_text": "24.8万円37.2万円",
      "area": 50.53,
      "area_text": "50.53m²",
      "walk_minutes": 8,
      "walk_text": "千駄ヶ谷駅",
      "station": "千駄ヶ谷",
      "age_years": 19,
      "age_text": "築19年",
      "image_url": "https://img01.suumo.com/front/gazo/fr/bukken/858/100476518858/100476518858_go.jpg",
      "address": "東京都新宿区大京町",
      "access": "東京メトロ丸ノ内線/四谷三丁目駅 歩7分 / 東京メトロ丸ノ内線/新宿御苑前駅 歩8分 / ＪＲ中央線/千駄ケ谷駅 歩8分"
    },
    {
      "source": "SUUMO",
      "type": "賃貸",
      "name": "サンクレイドル御苑内藤町",
      "detail_url": "https://suumo.jp/chintai/jnc_000104752936/",
      "price": 22.9,
      "price_text": "22.9万円10000円",
      "management_fee": 22.9,
      "management_fee_text": "22.9万円22.9万円",
      "area": 44.08,
      "area_text": "44.08m²",
      "walk_minutes": 6,
      "walk_text": "内藤町駅",
      "station": "内藤町",
      "age_years": 9,
      "age_text": "築9年",
      "image_url": "https://img01.suumo.com/front/gazo/fr/bukken/182/100487948182/100487948182_ro.jpg",
      "address": "東京都新宿区内藤町",
      "access": "東京メトロ丸ノ内線/新宿御苑前駅 歩6分 / 東京メトロ丸ノ内線/四谷三丁目駅 歩6分 / "
    },
    {
      "source": "HOMES",
      "type": "賃貸",
      "name": "オープンレジデンシア吉祥寺本町テラス",
      "detail_url": "https://www.homes.co.jp/chintai/room/73d70861371e53e4e4782e0292f4b2b9491b36ec/",
      "price": 23.5,
      "price_text": "23.5万円/-1ヶ月/1ヶ月/-/-",
      "management_fee": null,
      "management_fee_text": "1SLDK43.66m²",
      "area": 43.66,
      "area_text": "43.66m²",
      "walk_minutes": 10,
      "walk_text": "吉祥寺駅 徒歩10分",
      "station": "吉祥寺",
      "age_years": null,
      "age_text": "1年 / 4階建",
      "image_url": "https://image1.homes.jp/smallimg/image.php?file=http%3A%2F%2Fimg.homes.jp%2F116251%2Frent%2F297963%2F1%2F1%2F7ipj.jpg",
      "address": "東京都武蔵野市吉祥寺本町2丁目",
      "access": "JR中央線 吉祥寺駅 徒歩10分 / 京王井の頭線 井の頭公園駅 徒歩21分"
    }
  ],
  "new": [
    {
      "source": "SUUMO",
      "type": "新築",
      "name": "リビオ吉祥寺南町",
      "detail_url": "https://suumo.jp/ms/shinchiku/tokyo/sc_musashino/nc_67729878/",
      "price": null,
      "price_text": "価格未定",
      "area": 84.38,
      "area_text": "84.38m²～138.87m²",
      "walk_minutes": 7,
      "walk_text": "吉祥寺南町駅 徒歩7分",
      "station": "吉祥寺南町",
      "age_years": 0,
      "age_text": "新築",
      "image_url": "https://img01.suumo.com/jj/resizeImage?src=gazo%2Fbukken%2F030%2FN001000%2Fimg%2F78%2F67729878%2F67729878_000117.jpg&w=174&h=174",
      "address": "武蔵野市吉祥寺南町３",
      "access": "京王井の頭線/井の頭公園 徒歩7分"
    },
    {
      "source": "SUUMO",
      "type": "新築",
      "name": "プラウド吉祥寺本町",
      "detail_url": "https://suumo.jp/ms/shinchiku/tokyo/sc_musashino/nc_67730928/",
      "price": 12438,
      "price_text": "1億2438万円～1億3498万円",
      "area": 54.62,
      "area_text": "54.62m²～62.72m²",
      "walk_minutes": 6,
      "walk_text": "吉祥寺駅 徒歩6分",
      "station": "吉祥寺",
      "age_years": 0,
      "age_text": "新築",
      "image_url": "https://img01.suumo.com/jj/resizeImage?src=gazo%2Fbukken%2F030%2FN001000%2Fimg%2F28%2F67730928%2F67730928_000045.jpg&w=174&h=174",
      "address": "武蔵野市吉祥寺本町１",
      "access": "ＪＲ中央線/吉祥寺 徒歩6分"
    },
    {
      "source": "SUUMO",
      "type": "新築",
      "name": "ザ・パークハウス 吉祥寺プレイス",
      "detail_url": "https://suumo.jp/ms/shinchiku/tokyo/sc_musashino/nc_67729222/",
      "price": null,
      "price_text": "価格未定",
      "area": 63.61,
      "area_text": "63.61m²～104.82m²",
      "walk_minutes": 12,
      "walk_text": "吉祥寺駅 徒歩12分",
      "station": "吉祥寺",
      "age_years": 0,
      "age_text": "新築",
      "image_url": "https://img01.suumo.com/jj/resizeImage?src=gazo%2Fbukken%2F030%2FN001000%2Fimg%2F22%2F67729222%2F67729222_000206.jpg&w=174&h=174",
      "address": "武蔵野市吉祥寺北町１",
      "access": "ＪＲ中央線/吉祥寺 徒歩12分"
    },
    {
      "source": "SUUMO",
      "type": "新築",
      "name": "サンウッド吉祥寺南町一丁目",
      "detail_url": "https://suumo.jp/ms/shinchiku/tokyo/sc_musashino/nc_20315710/",
      "price": 15480,
      "price_text": "1億5480万円",
      "area": 54.11,
      "area_text": "54.11m²",
      "walk_minutes": 3,
      "walk_text": "吉祥寺駅 徒歩3分",
      "station": "吉祥寺",
      "age_years": 0,
      "age_text": "新築",
      "image_url": "https://img01.suumo.com/jj/resizeImage?src=gazo%2Fbukken%2F030%2FN010000%2Fimg%2F710%2F20315710%2F20315710_0001.jpg&w=174&h=174",
      "address": "東京都武蔵野市吉祥寺南町１",
      "access": "ＪＲ中央線/吉祥寺 徒歩3分"
    },
    {
      "source": "SUUMO",
      "type": "新築",
      "name": "オープンレジデンシア吉祥寺本町テラス",
      "detail_url": "https://suumo.jp/ms/shinchiku/tokyo/sc_musashino/nc_78674441/",
      "price": 18480,
      "price_text": "1億8480万円",
      "area": 81.1,
      "area_text": "81.1m²",
      "walk_minutes": 9,
      "walk_text": "吉祥寺駅 徒歩9分",
      "station": "吉祥寺",
      "age_years": 0,
      "age_text": "新築",
      "image_url": "https://img01.suumo.com/jj/resizeImage?src=gazo%2Fbukken%2F030%2FN010000%2Fimg%2F441%2F78674441%2F78674441_0100.jpg&w=174&h=174",
      "address": "東京都武蔵野市吉祥寺本町２",
      "access": "ＪＲ中央線/吉祥寺 徒歩9分"
    },
    {
      "source": "SUUMO",
      "type": "新築",
      "name": "プラウドタワー渋谷",
      "detail_url": "https://suumo.jp/ms/shinchiku/tokyo/sc_shibuya/nc_79020596/",
      "price": 22480,
      "price_text": "2億2480万円",
      "area": 61.4,
      "area_text": "61.4m²",
      "walk_minutes": 7,
      "walk_text": "渋谷駅 徒歩7分",
      "station": "渋谷",
      "age_years": 0,
      "age_text": "新築",
      "image_url": "https://img01.suumo.com/jj/resizeImage?src=gazo%2Fbukken%2F030%2FN010000%2Fimg%2F596%2F79020596%2F79020596_0020.jpg&w=174&h=174",
      "address": "東京都渋谷区渋谷３-3-10",
      "access": "ＪＲ山手線/渋谷 徒歩7分"
    },
    {
      "source": "SUUMO",
      "type": "新築",
      "name": "プラウドタワー渋谷",
      "detail_url": "https://suumo.jp/ms/shinchiku/tokyo/sc_shibuya/nc_78961344/",
      "price": 22480,
      "price_text": "2億2480万円",
      "area": 61.4,
      "area_text": "61.4m²",
      "walk_minutes": 6,
      "walk_text": "渋谷駅 徒歩6分",
      "station": "渋谷",
      "age_years": 0,
      "age_text": "新築",
      "image_url": "https://img01.suumo.com/jj/resizeImage?src=gazo%2Fbukken%2F030%2FN010000%2Fimg%2F344%2F78961344%2F78961344_0001.jpg&w=174&h=174",
      "address": "東京都渋谷区渋谷３",
      "access": "ＪＲ山手線/渋谷 徒歩6分"
    },
    {
      "source": "SUUMO",
      "type": "新築",
      "name": "プラウド渋谷東",
      "detail_url": "https://suumo.jp/ms/shinchiku/tokyo/sc_shibuya/nc_20664453/",
      "price": 22900,
      "price_text": "2億2900万円",
      "area": 61.11,
      "area_text": "61.11m²",
      "walk_minutes": 12,
      "walk_text": "渋谷駅 徒歩12分",
      "station": "渋谷",
      "age_years": 0,
      "age_text": "新築",
      "image_url": "https://img01.suumo.com/jj/resizeImage?src=gazo%2Fbukken%2F030%2FN010000%2Fimg%2F453%2F20664453%2F20664453_0001.jpg&w=174&h=174",
      "address": "東京都渋谷区東２",
      "access": "東急田園都市線/渋谷 徒歩12分"
    },
    {
      "source": "SUUMO",
      "type": "新築",
      "name": "プラウド渋谷東",
      "detail_url": "https://suumo.jp/ms/shinchiku/tokyo/sc_shibuya/nc_20662797/",
      "price": 22900,
      "price_text": "2億2900万円",
      "area": 61.11,
      "area_text": "61.11m²",
      "walk_minutes": 9,
      "walk_text": "渋谷駅 徒歩9分",
      "station": "渋谷",
      "age_years": 0,
      "age_text": "新築",
      "image_url": "https://img01.suumo.com/jj/resizeImage?src=gazo%2Fbukken%2F030%2FN010000%2Fimg%2F797%2F20662797%2F20662797_0002.jpg&w=174&h=174",
      "address": "東京都渋谷区東２-26-17",
      "access": "ＪＲ山手線/渋谷 徒歩9分"
    },
    {
      "source": "SUUMO",
      "type": "新築",
      "name": "プラウド渋谷東",
      "detail_url": "https://suumo.jp/ms/shinchiku/tokyo/sc_shibuya/nc_20559804/",
      "price": 22900,
      "price_text": "2億2900万円",
      "area": 61.11,
      "area_text": "61.11m²",
      "walk_minutes": 9,
      "walk_text": "渋谷駅 徒歩9分",
      "station": "渋谷",
      "age_years": 0,
      "age_text": "新築",
      "image_url": "https://img01.suumo.com/jj/resizeImage?src=gazo%2Fbukken%2F030%2FN010000%2Fimg%2F804%2F20559804%2F20559804_0008.jpg&w=174&h=174",
      "address": "東京都渋谷区東２",
      "access": "ＪＲ山手線/渋谷 徒歩9分"
    },
    {
      "source": "SUUMO",
      "type": "新築",
      "name": "プラウド渋谷東",
      "detail_url": "https://suumo.jp/ms/shinchiku/tokyo/sc_shibuya/nc_20246272/",
      "price": 22900,
      "price_text": "2億2900万円",
      "area": 61.11,
      "area_text": "61.11m²",
      "walk_minutes": 7,
      "walk_text": "渋谷駅 徒歩7分",
      "station": "渋谷",
      "age_years": 0,
      "age_text": "新築",
      "image_url": "https://img01.suumo.com/jj/resizeImage?src=gazo%2Fbukken%2F030%2FN010000%2Fimg%2F272%2F20246272%2F20246272_0001.jpg&w=174&h=174",
      "address": "東京都渋谷区東２",
      "access": "ＪＲ山手線/渋谷 徒歩7分"
    },
    {
      "source": "SUUMO",
      "type": "新築",
      "name": "プラウド渋谷東",
      "detail_url": "https://suumo.jp/ms/shinchiku/tokyo/sc_shibuya/nc_20152029/",
      "price": 22900,
      "price_text": "2億2900万円",
      "area": 61.11,
      "area_text": "61.11m²",
      "walk_minutes": 9,
      "walk_text": "渋谷駅 徒歩9分",
      "station": "渋谷",
      "age_years": 0,
      "age_text": "新築",
      "image_url": "https://img01.suumo.com/jj/resizeImage?src=gazo%2Fbukken%2F030%2FN010000%2Fimg%2F029%2F20152029%2F20152029_0006.jpg&w=174&h=174",
      "address": "東京都渋谷区東２",
      "access": "東急東横線/渋谷 徒歩9分"
    },
    {
      "source": "SUUMO",
      "type": "新築",
      "name": "プラウド渋谷東",
      "detail_url": "https://suumo.jp/ms/shinchiku/tokyo/sc_shibuya/nc_20145319/",
      "price": 22900,
      "price_text": "2億2900万円",
      "area": 61.11,
      "area_text": "61.11m²",
      "walk_minutes": 9,
      "walk_text": "渋谷駅 徒歩9分",
      "station": "渋谷",
      "age_years": 0,
      "age_text": "新築",
      "image_url": "https://img01.suumo.com/jj/resizeImage?src=gazo%2Fbukken%2F030%2FN010000%2Fimg%2F319%2F20145319%2F20145319_0034.jpg&w=174&h=174",
      "address": "東京都渋谷区東２-26-17",
      "access": "ＪＲ山手線/渋谷 徒歩9分"
    },
    {
      "source": "SUUMO",
      "type": "新築",
      "name": "プラウド渋谷東",
      "detail_url": "https://suumo.jp/ms/shinchiku/tokyo/sc_shibuya/nc_20094647/",
      "price": 22900,
      "price_text": "2億2900万円",
      "area": 61.11,
      "area_text": "61.11m²",
      "walk_minutes": 10,
      "walk_text": "渋谷駅 徒歩10分",
      "station": "渋谷",
      "age_years": 0,
      "age_text": "新築",
      "image_url": "https://img01.suumo.com/jj/resizeImage?src=gazo%2Fbukken%2F030%2FN010000%2Fimg%2F647%2F20094647%2F20094647_0001.jpg&w=174&h=174",
      "address": "東京都渋谷区東２",
      "access": "ＪＲ山手線/渋谷 徒歩10分"
    },
    {
      "source": "SUUMO",
      "type": "新築",
      "name": "プラウドタワー渋谷",
      "detail_url": "https://suumo.jp/ms/shinchiku/tokyo/sc_shibuya/nc_20594928/",
      "price": 24000,
      "price_text": "2億4000万円",
      "area": 74.47,
      "area_text": "74.47m²",
      "walk_minutes": 5,
      "walk_text": "渋谷駅 徒歩5分",
      "station": "渋谷",
      "age_years": 0,
      "age_text": "新築",
      "image_url": "https://img01.suumo.com/jj/resizeImage?src=gazo%2Fbukken%2F030%2FN010000%2Fimg%2F928%2F20594928%2F20594928_0001.jpg&w=174&h=174",
      "address": "東京都渋谷区渋谷３",
      "access": "ＪＲ山手線/渋谷 徒歩5分"
    },
    {
      "source": "SUUMO",
      "type": "新築",
      "name": "プラウド四谷",
      "detail_url": "https://suumo.jp/ms/shinchiku/tokyo/sc_shinjuku/nc_67734365/",
      "price": null,
      "price_text": "価格未定",
      "area": 70.07,
      "area_text": "70.07m²～84.42m²",
      "walk_minutes": 3,
      "walk_text": "四ツ谷駅 徒歩3分",
      "station": "四ツ谷",
      "age_years": 0,
      "age_text": "新築",
      "image_url": "https://img01.suumo.com/jj/resizeImage?src=gazo%2Fbukken%2F030%2FN001000%2Fimg%2F65%2F67734365%2F67734365_000061.jpg&w=174&h=174",
      "address": "新宿区四谷１",
      "access": "ＪＲ中央線/四ツ谷 徒歩3分"
    }
  ],
  "used": [
    {
      "source": "SUUMO",
      "type": "中古",
      "name": "サンウッド吉祥寺南町一丁目",
      "detail_url": "https://suumo.jp/ms/chuko/tokyo/sc_musashino/nc_20564565/",
      "price": 11980,
      "price_text": "1億1980万円",
      "area": 45.36,
      "area_text": "45.36m2（13.72坪）（壁芯）",
      "walk_minutes": 3,
      "walk_text": "吉祥寺駅 徒歩3分",
      "station": "吉祥寺",
      "age_years": 1,
      "age_text": "2025年10月",
      "image_url": "https://img01.suumo.com/jj/resizeImage?src=gazo%2Fbukken%2F030%2FN010000%2Fimg%2F565%2F20564565%2F20564565_0009.jpg&w=192&h=144",
      "address": "東京都武蔵野市吉祥寺南町１",
      "access": "ＪＲ総武線「吉祥寺」徒歩3分"
    },
    {
      "source": "SUUMO",
      "type": "中古",
      "name": "ルジェンテ吉祥寺",
      "detail_url": "https://suumo.jp/ms/chuko/tokyo/sc_musashino/nc_78280842/",
      "price": 11980,
      "price_text": "1億1980万円",
      "area": 60.65,
      "area_text": "60.65m2（18.34坪）（壁芯）",
      "walk_minutes": 4,
      "walk_text": "吉祥寺駅 徒歩4分",
      "station": "吉祥寺",
      "age_years": 18,
      "age_text": "2008年11月",
      "image_url": "https://img01.suumo.com/jj/resizeImage?src=gazo%2Fbukken%2F030%2FN010000%2Fimg%2F842%2F78280842%2F78280842_0031.jpg&w=192&h=144",
      "address": "東京都武蔵野市吉祥寺南町２",
      "access": "ＪＲ中央線「吉祥寺」徒歩4分"
    },
    {
      "source": "SUUMO",
      "type": "中古",
      "name": "井の頭公園パークハウス吉祥寺南町",
      "detail_url": "https://suumo.jp/ms/chuko/tokyo/sc_musashino/nc_20394756/",
      "price": 24800,
      "price_text": "2億4800万円",
      "area": 96.56,
      "area_text": "96.56m2（壁芯）",
      "walk_minutes": 9,
      "walk_text": "吉祥寺駅 徒歩9分",
      "station": "吉祥寺",
      "age_years": 0,
      "age_text": "2026年1月",
      "image_url": "https://img01.suumo.com/jj/resizeImage?src=gazo%2Fbukken%2F030%2FN010000%2Fimg%2F756%2F20394756%2F20394756_0001.jpg&w=192&h=144",
      "address": "東京都武蔵野市吉祥寺南町３",
      "access": "ＪＲ中央線「吉祥寺」徒歩9分"
    },
    {
      "source": "SUUMO",
      "type": "中古",
      "name": "プラネスーペリア御殿山井の頭公園",
      "detail_url": "https://suumo.jp/ms/chuko/tokyo/sc_musashino/nc_78668650/",
      "price": 12990,
      "price_text": "1億2990万円",
      "area": 71.78,
      "area_text": "71.78m2（21.71坪）（壁芯）",
      "walk_minutes": 9,
      "walk_text": "御殿山駅 徒歩9分",
      "station": "御殿山",
      "age_years": 12,
      "age_text": "2014年1月",
      "image_url": "https://img01.suumo.com/jj/resizeImage?src=gazo%2Fbukken%2F030%2FN010000%2Fimg%2F650%2F78668650%2F78668650_0023.jpg&w=192&h=144",
      "address": "東京都武蔵野市御殿山２",
      "access": "ＪＲ中央線「三鷹」徒歩9分"
    },
    {
      "source": "SUUMO",
      "type": "中古",
      "name": "プラネスーペリア御殿山　井の頭公園",
      "detail_url": "https://suumo.jp/ms/chuko/tokyo/sc_musashino/nc_20503725/",
      "price": 14900,
      "price_text": "1億4900万円",
      "area": 71.78,
      "area_text": "71.78m2（21.71坪）（壁芯）",
      "walk_minutes": 9,
      "walk_text": "御殿山駅 徒歩9分",
      "station": "御殿山",
      "age_years": 12,
      "age_text": "2014年1月",
      "image_url": "https://img01.suumo.com/jj/resizeImage?src=gazo%2Fbukken%2F030%2FN010000%2Fimg%2F725%2F20503725%2F20503725_0001.jpg&w=192&h=144",
      "address": "東京都武蔵野市御殿山２",
      "access": "ＪＲ中央線「三鷹」徒歩9分"
    },
    {
      "source": "SUUMO",
      "type": "中古",
      "name": "ルフォン井の頭公園",
      "detail_url": "https://suumo.jp/ms/chuko/tokyo/sc_musashino/nc_20503722/",
      "price": 15980,
      "price_text": "1億5980万円",
      "area": 74.7,
      "area_text": "74.7m2（22.59坪）（壁芯）",
      "walk_minutes": 11,
      "walk_text": "御殿山駅 徒歩11分",
      "station": "御殿山",
      "age_years": 14,
      "age_text": "2012年2月",
      "image_url": "https://img01.suumo.com/jj/resizeImage?src=gazo%2Fbukken%2F030%2FN010000%2Fimg%2F722%2F20503722%2F20503722_0001.jpg&w=192&h=144",
      "address": "東京都武蔵野市御殿山２",
      "access": "ＪＲ中央線「三鷹」徒歩11分"
    },
    {
      "source": "SUUMO",
      "type": "中古",
      "name": "ルフォン吉祥寺",
      "detail_url": "https://suumo.jp/ms/chuko/tokyo/sc_musashino/nc_20390486/",
      "price": 24780,
      "price_text": "2億4780万円",
      "area": 107.14,
      "area_text": "107.14m2（壁芯）",
      "walk_minutes": 11,
      "walk_text": "御殿山駅 徒歩11分",
      "station": "御殿山",
      "age_years": 18,
      "age_text": "2008年10月",
      "image_url": "https://img01.suumo.com/jj/resizeImage?src=gazo%2Fbukken%2F030%2FN010000%2Fimg%2F486%2F20390486%2F20390486_0001.jpg&w=192&h=144",
      "address": "東京都武蔵野市御殿山２",
      "access": "ＪＲ中央線「三鷹」徒歩11分"
    },
    {
      "source": "SUUMO",
      "type": "中古",
      "name": "ルフォン吉祥寺",
      "detail_url": "https://suumo.jp/ms/chuko/tokyo/sc_musashino/nc_79071425/",
      "price": 25980,
      "price_text": "2億5980万円",
      "area": 107.14,
      "area_text": "107.14m2",
      "walk_minutes": 11,
      "walk_text": "御殿山駅 徒歩11分",
      "station": "御殿山",
      "age_years": 18,
      "age_text": "2008年10月",
      "image_url": "https://img01.suumo.com/jj/resizeImage?src=gazo%2Fbukken%2F030%2FN010000%2Fimg%2F425%2F79071425%2F79071425_0019.jpg&w=192&h=144",
      "address": "東京都武蔵野市御殿山２",
      "access": "ＪＲ中央線「三鷹」徒歩11分"
    },
    {
      "source": "SUUMO",
      "type": "中古",
      "name": "パークコート神宮北参道　ザ　タワー",
      "detail_url": "https://suumo.jp/ms/chuko/tokyo/sc_shibuya/nc_20054220/",
      "price": 16480,
      "price_text": "1億6480万円",
      "area": 42.55,
      "area_text": "42.55m2（壁芯）",
      "walk_minutes": 1,
      "walk_text": "千駄ヶ谷駅 徒歩1分",
      "station": "千駄ヶ谷",
      "age_years": 3,
      "age_text": "2023年1月",
      "image_url": "https://img01.suumo.com/jj/resizeImage?src=gazo%2Fbukken%2F030%2FN010000%2Fimg%2F220%2F20054220%2F20054220_0001.jpg&w=192&h=144",
      "address": "東京都渋谷区千駄ヶ谷４",
      "access": "東京メトロ副都心線「北参道」徒歩1分"
    },
    {
      "source": "SUUMO",
      "type": "中古",
      "name": "THE　KITA",
      "detail_url": "https://suumo.jp/ms/chuko/tokyo/sc_shibuya/nc_78063221/",
      "price": 69800,
      "price_text": "6億9800万円",
      "area": 123.96,
      "area_text": "123.96m2（壁芯）",
      "walk_minutes": 6,
      "walk_text": "千駄ヶ谷駅 徒歩6分",
      "station": "千駄ヶ谷",
      "age_years": 6,
      "age_text": "2020年7月",
      "image_url": "https://img01.suumo.com/jj/resizeImage?src=gazo%2Fbukken%2F030%2FN010000%2Fimg%2F221%2F78063221%2F78063221_0001.jpg&w=192&h=144",
      "address": "東京都渋谷区千駄ヶ谷３",
      "access": "東京メトロ副都心線「北参道」徒歩6分"
    },
    {
      "source": "SUUMO",
      "type": "中古",
      "name": "マジェスティハウス新宿御苑パークナード",
      "detail_url": "https://suumo.jp/ms/chuko/tokyo/sc_shinjuku/nc_79051221/",
      "price": 16980,
      "price_text": "1億6980万円",
      "area": 74.04,
      "area_text": "74.04m2",
      "walk_minutes": 10,
      "walk_text": "大京町駅 徒歩10分",
      "station": "大京町",
      "age_years": 12,
      "age_text": "2014年1月",
      "image_url": "https://img01.suumo.com/jj/resizeImage?src=gazo%2Fbukken%2F030%2FN010000%2Fimg%2F221%2F79051221%2F79051221_0001.jpg&w=192&h=144",
      "address": "東京都新宿区大京町",
      "access": "東京メトロ丸ノ内線「四谷三丁目」徒歩10分"
    },
    {
      "source": "SUUMO",
      "type": "中古",
      "name": "VECS♪マジェスティハウス新宿御苑パークナード",
      "detail_url": "https://suumo.jp/ms/chuko/tokyo/sc_shinjuku/nc_78727043/",
      "price": 25500,
      "price_text": "2億5500万円",
      "area": 90.22,
      "area_text": "90.22m2（壁芯）",
      "walk_minutes": 8,
      "walk_text": "大京町駅 徒歩8分",
      "station": "大京町",
      "age_years": 12,
      "age_text": "2014年2月",
      "image_url": "https://img01.suumo.com/jj/resizeImage?src=gazo%2Fbukken%2F030%2FN010000%2Fimg%2F043%2F78727043%2F78727043_0004.jpg&w=192&h=144",
      "address": "東京都新宿区大京町",
      "access": "都営大江戸線「国立競技場」徒歩8分"
    },
    {
      "source": "SUUMO",
      "type": "中古",
      "name": "マジェスティハウス新宿御苑パークナード",
      "detail_url": "https://suumo.jp/ms/chuko/tokyo/sc_shinjuku/nc_78681542/",
      "price": 13500,
      "price_text": "1億3500万円",
      "area": 55.95,
      "area_text": "55.95m2（壁芯）",
      "walk_minutes": 7,
      "walk_text": "大京町駅 徒歩7分",
      "station": "大京町",
      "age_years": 12,
      "age_text": "2014年1月",
      "image_url": "https://img01.suumo.com/jj/resizeImage?src=gazo%2Fbukken%2F030%2FN010000%2Fimg%2F542%2F78681542%2F78681542_0009.jpg&w=192&h=144",
      "address": "東京都新宿区大京町",
      "access": "都営大江戸線「国立競技場」徒歩7分"
    },
    {
      "source": "SUUMO",
      "type": "中古",
      "name": "プラウド新宿御苑エンパイア",
      "detail_url": "https://suumo.jp/ms/chuko/tokyo/sc_shinjuku/nc_20342635/",
      "price": 18980,
      "price_text": "1億8980万円",
      "area": 69.34,
      "area_text": "69.34m2（壁芯）",
      "walk_minutes": 5,
      "walk_text": "大京町駅 徒歩5分",
      "station": "大京町",
      "age_years": 1,
      "age_text": "2025年8月",
      "image_url": "https://img01.suumo.com/jj/resizeImage?src=gazo%2Fbukken%2F030%2FN010000%2Fimg%2F635%2F20342635%2F20342635_0001.jpg&w=192&h=144",
      "address": "東京都新宿区大京町",
      "access": "都営大江戸線「国立競技場」徒歩5分"
    },
    {
      "source": "SUUMO",
      "type": "中古",
      "name": "マジェスティハウス新宿御苑パークナード",
      "detail_url": "https://suumo.jp/ms/chuko/tokyo/sc_shinjuku/nc_20496669/",
      "price": 19800,
      "price_text": "1億9800万円",
      "area": 71.1,
      "area_text": "71.1m2（21.50坪）（壁芯）",
      "walk_minutes": 7,
      "walk_text": "大京町駅 徒歩7分",
      "station": "大京町",
      "age_years": 12,
      "age_text": "2014年1月",
      "image_url": "https://img01.suumo.com/jj/resizeImage?src=gazo%2Fbukken%2F030%2FN010000%2Fimg%2F669%2F20496669%2F20496669_0001.jpg&w=192&h=144",
      "address": "東京都新宿区大京町",
      "access": "都営大江戸線「国立競技場」徒歩7分"
    },
    {
      "source": "SUUMO",
      "type": "中古",
      "name": "マジェスティハウス新宿御苑パークナード",
      "detail_url": "https://suumo.jp/ms/chuko/tokyo/sc_shinjuku/nc_20417672/",
      "price": 21000,
      "price_text": "2億1000万円",
      "area": 74.04,
      "area_text": "74.04m2（壁芯）",
      "walk_minutes": 7,
      "walk_text": "大京町駅 徒歩7分",
      "station": "大京町",
      "age_years": 12,
      "age_text": "2014年1月",
      "image_url": "https://img01.suumo.com/jj/resizeImage?src=gazo%2Fbukken%2F030%2FN010000%2Fimg%2F672%2F20417672%2F20417672_0003.jpg&w=192&h=144",
      "address": "東京都新宿区大京町",
      "access": "都営大江戸線「国立競技場」徒歩7分"
    },
    {
      "source": "SUUMO",
      "type": "中古",
      "name": "マジェスティハウス新宿御苑パークナード",
      "detail_url": "https://suumo.jp/ms/chuko/tokyo/sc_shinjuku/nc_20153655/",
      "price": 25500,
      "price_text": "2億5500万円",
      "area": 90.22,
      "area_text": "90.22m2（壁芯）",
      "walk_minutes": 8,
      "walk_text": "大京町駅 徒歩8分",
      "station": "大京町",
      "age_years": 12,
      "age_text": "2014年1月",
      "image_url": "https://img01.suumo.com/jj/resizeImage?src=gazo%2Fbukken%2F030%2FN010000%2Fimg%2F655%2F20153655%2F20153655_0009.jpg&w=192&h=144",
      "address": "東京都新宿区大京町",
      "access": "都営大江戸線「国立競技場」徒歩8分"
    },
    {
      "source": "SUUMO",
      "type": "中古",
      "name": "マジェスティハウス新宿御苑パークナード",
      "detail_url": "https://suumo.jp/ms/chuko/tokyo/sc_shinjuku/nc_78466132/",
      "price": 25500,
      "price_text": "2億5500万円",
      "area": 90.22,
      "area_text": "90.22m2（壁芯）",
      "walk_minutes": 7,
      "walk_text": "大京町駅 徒歩7分",
      "station": "大京町",
      "age_years": 12,
      "age_text": "2014年1月",
      "image_url": "https://img01.suumo.com/jj/resizeImage?src=gazo%2Fbukken%2F030%2FN010000%2Fimg%2F132%2F78466132%2F78466132_0001.jpg&w=192&h=144",
      "address": "東京都新宿区大京町",
      "access": "都営大江戸線「国立競技場」徒歩7分"
    },
    {
      "source": "SUUMO",
      "type": "中古",
      "name": "マジェスティハウス新宿御苑パークナード",
      "detail_url": "https://suumo.jp/ms/chuko/tokyo/sc_shinjuku/nc_78868985/",
      "price": 25500,
      "price_text": "2億5500万円",
      "area": 90.22,
      "area_text": "90.22m2（壁芯）",
      "walk_minutes": 8,
      "walk_text": "大京町駅 徒歩8分",
      "station": "大京町",
      "age_years": 12,
      "age_text": "2014年1月",
      "image_url": "https://img01.suumo.com/jj/resizeImage?src=gazo%2Fbukken%2F030%2FN010000%2Fimg%2F985%2F78868985%2F78868985_0007.jpg&w=192&h=144",
      "address": "東京都新宿区大京町",
      "access": "都営大江戸線「国立競技場」徒歩8分"
    },
    {
      "source": "SUUMO",
      "type": "中古",
      "name": "プラウド新宿御苑エンパイア",
      "detail_url": "https://suumo.jp/ms/chuko/tokyo/sc_shinjuku/nc_20612457/",
      "price": 55000,
      "price_text": "5億5000万円",
      "area": 110.19,
      "area_text": "110.19m2（33.33坪）（壁芯）",
      "walk_minutes": 5,
      "walk_text": "大京町駅 徒歩5分",
      "station": "大京町",
      "age_years": 16,
      "age_text": "2010年6月",
      "image_url": "https://img01.suumo.com/jj/resizeImage?src=gazo%2Fbukken%2F030%2FN010000%2Fimg%2F457%2F20612457%2F20612457_0001.jpg&w=192&h=144",
      "address": "東京都新宿区大京町",
      "access": "都営大江戸線「国立競技場」徒歩5分"
    },
    {
      "source": "SUUMO",
      "type": "中古",
      "name": "ジオ御苑内藤町",
      "detail_url": "https://suumo.jp/ms/chuko/tokyo/sc_shinjuku/nc_20246769/",
      "price": 13980,
      "price_text": "1億3980万円",
      "area": 60.11,
      "area_text": "60.11m2（壁芯）",
      "walk_minutes": 8,
      "walk_text": "内藤町駅 徒歩8分",
      "station": "内藤町",
      "age_years": 10,
      "age_text": "2016年3月",
      "image_url": "https://img01.suumo.com/jj/resizeImage?src=gazo%2Fbukken%2F030%2FN010000%2Fimg%2F769%2F20246769%2F20246769_0001.jpg&w=192&h=144",
      "address": "東京都新宿区内藤町",
      "access": "東京メトロ丸ノ内線「四谷三丁目」徒歩8分"
    },
    {
      "source": "SUUMO",
      "type": "中古",
      "name": "ディアナコート御苑内藤町",
      "detail_url": "https://suumo.jp/ms/chuko/tokyo/sc_shinjuku/nc_20212283/",
      "price": 18980,
      "price_text": "1億8980万円",
      "area": 63.5,
      "area_text": "63.5m2（壁芯）",
      "walk_minutes": 7,
      "walk_text": "内藤町駅 徒歩7分",
      "station": "内藤町",
      "age_years": 6,
      "age_text": "2020年3月",
      "image_url": "https://img01.suumo.com/jj/resizeImage?src=gazo%2Fbukken%2F030%2FN010000%2Fimg%2F283%2F20212283%2F20212283_0003.jpg&w=192&h=144",
      "address": "東京都新宿区内藤町",
      "access": "東京メトロ丸ノ内線「四谷三丁目」徒歩7分"
    },
    {
      "source": "SUUMO",
      "type": "中古",
      "name": "THE 新宿御苑フロントプロジェクト｜新規リノベーシ…",
      "detail_url": "https://suumo.jp/ms/chuko/tokyo/sc_shinjuku/nc_20636709/",
      "price": 32980,
      "price_text": "3億2980万円",
      "area": 85.75,
      "area_text": "85.75m2（壁芯）",
      "walk_minutes": 6,
      "walk_text": "内藤町駅 徒歩6分",
      "station": "内藤町",
      "age_years": 17,
      "age_text": "2009年1月",
      "image_url": "https://img01.suumo.com/jj/resizeImage?src=gazo%2Fbukken%2F030%2FN010000%2Fimg%2F709%2F20636709%2F20636709_0089.jpg&w=192&h=144",
      "address": "東京都新宿区内藤町",
      "access": "東京メトロ丸ノ内線「新宿御苑前」徒歩6分"
    },
    {
      "source": "SUUMO",
      "type": "中古",
      "name": "フォルム内藤町",
      "detail_url": "https://suumo.jp/ms/chuko/tokyo/sc_shinjuku/nc_79134743/",
      "price": 35990,
      "price_text": "3億5990万円",
      "area": 101.31,
      "area_text": "101.31m2（30.64坪）（壁芯）",
      "walk_minutes": 6,
      "walk_text": "内藤町駅 徒歩6分",
      "station": "内藤町",
      "age_years": 17,
      "age_text": "2009年1月",
      "image_url": "https://img01.suumo.com/jj/resizeImage?src=gazo%2Fbukken%2F030%2FN010000%2Fimg%2F743%2F79134743%2F79134743_0046.jpg&w=192&h=144",
      "address": "東京都新宿区内藤町1-2",
      "access": "東京メトロ丸ノ内線「新宿御苑前」徒歩6分"
    },
    {
      "source": "SUUMO",
      "type": "中古",
      "name": "ディアナコート御苑内藤町",
      "detail_url": "https://suumo.jp/ms/chuko/tokyo/sc_shinjuku/nc_20186845/",
      "price": 18000,
      "price_text": "1億8000万円",
      "area": 66.81,
      "area_text": "66.81m2（20.20坪）（壁芯）",
      "walk_minutes": 6,
      "walk_text": "内藤町駅 徒歩6分",
      "station": "内藤町",
      "age_years": 6,
      "age_text": "2020年2月",
      "image_url": "https://img01.suumo.com/jj/resizeImage?src=gazo%2Fbukken%2F030%2FN010000%2Fimg%2F845%2F20186845%2F20186845_0016.jpg&w=192&h=144",
      "address": "東京都新宿区内藤町",
      "access": "東京メトロ丸ノ内線「四谷三丁目」徒歩6分"
    },
    {
      "source": "SUUMO",
      "type": "中古",
      "name": "ディアナコート御苑内藤町",
      "detail_url": "https://suumo.jp/ms/chuko/tokyo/sc_shinjuku/nc_20186846/",
      "price": 18980,
      "price_text": "1億8980万円",
      "area": 63.5,
      "area_text": "63.5m2（19.20坪）（壁芯）",
      "walk_minutes": 6,
      "walk_text": "内藤町駅 徒歩6分",
      "station": "内藤町",
      "age_years": 6,
      "age_text": "2020年3月",
      "image_url": "https://img01.suumo.com/jj/resizeImage?src=gazo%2Fbukken%2F030%2FN010000%2Fimg%2F846%2F20186846%2F20186846_0021.jpg&w=192&h=144",
      "address": "東京都新宿区内藤町",
      "access": "東京メトロ丸ノ内線「四谷三丁目」徒歩6分"
    },
    {
      "source": "SUUMO",
      "type": "中古",
      "name": "ディアナコート御苑内藤町",
      "detail_url": "https://suumo.jp/ms/chuko/tokyo/sc_shinjuku/nc_20629168/",
      "price": 18980,
      "price_text": "1億8980万円",
      "area": 63.5,
      "area_text": "63.5m2（壁芯）",
      "walk_minutes": 6,
      "walk_text": "内藤町駅 徒歩6分",
      "station": "内藤町",
      "age_years": 6,
      "age_text": "2020年3月",
      "image_url": "https://img01.suumo.com/jj/resizeImage?src=gazo%2Fbukken%2F030%2FN010000%2Fimg%2F168%2F20629168%2F20629168_0006.jpg&w=192&h=144",
      "address": "東京都新宿区内藤町",
      "access": "東京メトロ丸ノ内線「四谷三丁目」徒歩6分"
    },
    {
      "source": "SUUMO",
      "type": "中古",
      "name": "フォルム内藤町14F",
      "detail_url": "https://suumo.jp/ms/chuko/tokyo/sc_shinjuku/nc_20647705/",
      "price": 32000,
      "price_text": "3億2000万円",
      "area": 92.56,
      "area_text": "92.56m2（壁芯）",
      "walk_minutes": 5,
      "walk_text": "内藤町駅 徒歩5分",
      "station": "内藤町",
      "age_years": 17,
      "age_text": "2009年1月",
      "image_url": "https://img01.suumo.com/jj/resizeImage?src=gazo%2Fbukken%2Fsystem%2Fimg%2FDummy_Photo_011_132_99.jpg&w=192&h=144",
      "address": "東京都新宿区内藤町",
      "access": "東京メトロ丸ノ内線「新宿御苑前」徒歩5分"
    },
    {
      "source": "SUUMO",
      "type": "中古",
      "name": "フォルム内藤町 新宿御苑前｜駅歩6分｜新規リノベーシ…",
      "detail_url": "https://suumo.jp/ms/chuko/tokyo/sc_shinjuku/nc_20416827/",
      "price": 32980,
      "price_text": "3億2980万円",
      "area": 85.75,
      "area_text": "85.75m2（壁芯）",
      "walk_minutes": 6,
      "walk_text": "内藤町駅 徒歩6分",
      "station": "内藤町",
      "age_years": 17,
      "age_text": "2009年1月",
      "image_url": "https://img01.suumo.com/jj/resizeImage?src=gazo%2Fbukken%2F030%2FN010000%2Fimg%2F827%2F20416827%2F20416827_0114.jpg&w=192&h=144",
      "address": "東京都新宿区内藤町",
      "access": "東京メトロ丸ノ内線「新宿御苑前」徒歩6分"
    },
    {
      "source": "SUUMO",
      "type": "中古",
      "name": "ジオ御苑内藤町",
      "detail_url": "https://suumo.jp/ms/chuko/tokyo/sc_shinjuku/nc_20212271/",
      "price": 62800,
      "price_text": "6億2800万円",
      "area": 112.14,
      "area_text": "112.14m2（壁芯）",
      "walk_minutes": 7,
      "walk_text": "内藤町駅 徒歩7分",
      "station": "内藤町",
      "age_years": 10,
      "age_text": "2016年3月",
      "image_url": "https://img01.suumo.com/jj/resizeImage?src=gazo%2Fbukken%2F030%2FN010000%2Fimg%2F271%2F20212271%2F20212271_0010.jpg&w=192&h=144",
      "address": "東京都新宿区内藤町",
      "access": "東京メトロ丸ノ内線「四谷三丁目」徒歩7分"
    },
    {
      "source": "SUUMO",
      "type": "中古",
      "name": "クラッシィタワー新宿御苑",
      "detail_url": "https://suumo.jp/ms/chuko/tokyo/sc_shinjuku/nc_20553154/",
      "price": 17600,
      "price_text": "1億7600万円",
      "area": 56.1,
      "area_text": "56.1m2（16.97坪）（壁芯）",
      "walk_minutes": 4,
      "walk_text": "四谷駅 徒歩4分",
      "station": "四谷",
      "age_years": 2,
      "age_text": "2024年10月",
      "image_url": "https://img01.suumo.com/jj/resizeImage?src=gazo%2Fbukken%2F030%2FN010000%2Fimg%2F154%2F20553154%2F20553154_0001.jpg&w=192&h=144",
      "address": "東京都新宿区四谷４-29-3",
      "access": "東京メトロ丸ノ内線「新宿御苑前」徒歩4分"
    },
    {
      "source": "SUUMO",
      "type": "中古",
      "name": "ライオンズ四谷タワーゲート",
      "detail_url": "https://suumo.jp/ms/chuko/tokyo/sc_shinjuku/nc_78586303/",
      "price": 19990,
      "price_text": "1億9990万円",
      "area": 79.02,
      "area_text": "79.02m2（壁芯）",
      "walk_minutes": 5,
      "walk_text": "四谷駅 徒歩5分",
      "station": "四谷",
      "age_years": 19,
      "age_text": "2007年5月",
      "image_url": "https://img01.suumo.com/jj/resizeImage?src=gazo%2Fbukken%2F030%2FN010000%2Fimg%2F303%2F78586303%2F78586303_0030.jpg&w=192&h=144",
      "address": "東京都新宿区四谷４",
      "access": "東京メトロ丸ノ内線「四谷三丁目」徒歩5分"
    },
    {
      "source": "SUUMO",
      "type": "中古",
      "name": "クラッシィタワー新宿御苑",
      "detail_url": "https://suumo.jp/ms/chuko/tokyo/sc_shinjuku/nc_78857955/",
      "price": 29000,
      "price_text": "2億9000万円",
      "area": 74.92,
      "area_text": "74.92m2（壁芯）",
      "walk_minutes": 4,
      "walk_text": "四谷駅 徒歩4分",
      "station": "四谷",
      "age_years": 2,
      "age_text": "2024年10月",
      "image_url": "https://img01.suumo.com/jj/resizeImage?src=gazo%2Fbukken%2F030%2FN010000%2Fimg%2F955%2F78857955%2F78857955_0102.jpg&w=192&h=144",
      "address": "東京都新宿区四谷４",
      "access": "東京メトロ丸ノ内線「新宿御苑前」徒歩4分"
    },
    {
      "source": "SUUMO",
      "type": "中古",
      "name": "クラッシィタワー新宿御苑1905号室",
      "detail_url": "https://suumo.jp/ms/chuko/tokyo/sc_shinjuku/nc_20488546/",
      "price": 29900,
      "price_text": "2億9900万円",
      "area": 79.14,
      "area_text": "79.14m2（壁芯）",
      "walk_minutes": 4,
      "walk_text": "四谷駅 徒歩4分",
      "station": "四谷",
      "age_years": 2,
      "age_text": "2024年10月",
      "image_url": "https://img01.suumo.com/jj/resizeImage?src=gazo%2Fbukken%2F030%2FN010000%2Fimg%2F546%2F20488546%2F20488546_0001.jpg&w=192&h=144",
      "address": "東京都新宿区四谷４-29-3",
      "access": "東京メトロ丸ノ内線「新宿御苑前」徒歩4分"
    },
    {
      "source": "SUUMO",
      "type": "中古",
      "name": "クラッシィタワー新宿御苑",
      "detail_url": "https://suumo.jp/ms/chuko/tokyo/sc_shinjuku/nc_78725482/",
      "price": 32800,
      "price_text": "3億2800万円",
      "area": 74.92,
      "area_text": "74.92m2（壁芯）",
      "walk_minutes": 4,
      "walk_text": "四谷駅 徒歩4分",
      "station": "四谷",
      "age_years": 2,
      "age_text": "2024年10月",
      "image_url": "https://img01.suumo.com/jj/resizeImage?src=gazo%2Fbukken%2F030%2FN010000%2Fimg%2F482%2F78725482%2F78725482_0040.jpg&w=192&h=144",
      "address": "東京都新宿区四谷４",
      "access": "東京メトロ丸ノ内線「新宿御苑前」徒歩4分"
    },
    {
      "source": "SUUMO",
      "type": "中古",
      "name": "クラッシィタワー新宿御苑",
      "detail_url": "https://suumo.jp/ms/chuko/tokyo/sc_shinjuku/nc_20347740/",
      "price": 34800,
      "price_text": "3億4800万円",
      "area": 79.98,
      "area_text": "79.98m2（24.19坪）（壁芯）",
      "walk_minutes": 4,
      "walk_text": "四谷駅 徒歩4分",
      "station": "四谷",
      "age_years": 2,
      "age_text": "2024年10月",
      "image_url": "https://img01.suumo.com/jj/resizeImage?src=gazo%2Fbukken%2F030%2FN010000%2Fimg%2F740%2F20347740%2F20347740_0034.jpg&w=192&h=144",
      "address": "東京都新宿区四谷４",
      "access": "東京メトロ丸ノ内線「新宿御苑前」徒歩4分"
    },
    {
      "source": "SUUMO",
      "type": "中古",
      "name": "クラッシィタワー新宿御苑",
      "detail_url": "https://suumo.jp/ms/chuko/tokyo/sc_shinjuku/nc_78790755/",
      "price": 29000,
      "price_text": "2億9000万円",
      "area": 74.92,
      "area_text": "74.92m2（壁芯）",
      "walk_minutes": 5,
      "walk_text": "四谷駅 徒歩5分",
      "station": "四谷",
      "age_years": 2,
      "age_text": "2024年10月",
      "image_url": "https://img01.suumo.com/jj/resizeImage?src=gazo%2Fbukken%2F030%2FN010000%2Fimg%2F755%2F78790755%2F78790755_0009.jpg&w=192&h=144",
      "address": "東京都新宿区四谷４",
      "access": "東京メトロ丸ノ内線「新宿御苑前」徒歩5分"
    },
    {
      "source": "SUUMO",
      "type": "中古",
      "name": "クラッシィタワー新宿御苑",
      "detail_url": "https://suumo.jp/ms/chuko/tokyo/sc_shinjuku/nc_78937109/",
      "price": 29000,
      "price_text": "2億9000万円",
      "area": 74.92,
      "area_text": "74.92m2（壁芯）",
      "walk_minutes": 4,
      "walk_text": "四谷駅 徒歩4分",
      "station": "四谷",
      "age_years": 2,
      "age_text": "2024年10月",
      "image_url": "https://img01.suumo.com/jj/resizeImage?src=gazo%2Fbukken%2F030%2FN010000%2Fimg%2F109%2F78937109%2F78937109_0024.jpg&w=192&h=144",
      "address": "東京都新宿区四谷４",
      "access": "東京メトロ丸ノ内線「新宿御苑前」徒歩4分"
    },
    {
      "source": "SUUMO",
      "type": "中古",
      "name": "クラッシィタワー新宿御苑",
      "detail_url": "https://suumo.jp/ms/chuko/tokyo/sc_shinjuku/nc_20333866/",
      "price": 63980,
      "price_text": "6億3980万円",
      "area": 117.73,
      "area_text": "117.73m2（35.61坪）（壁芯）",
      "walk_minutes": 5,
      "walk_text": "四谷駅 徒歩5分",
      "station": "四谷",
      "age_years": 2,
      "age_text": "2024年10月",
      "image_url": "https://img01.suumo.com/jj/resizeImage?src=gazo%2Fbukken%2F030%2FN010000%2Fimg%2F866%2F20333866%2F20333866_0019.jpg&w=192&h=144",
      "address": "東京都新宿区四谷４",
      "access": "東京メトロ丸ノ内線「新宿御苑前」徒歩5分"
    },
    {
      "source": "cowcamo",
      "type": "中古",
      "name": "いいのかしら？",
      "detail_url": "https://cowcamo.jp/%E6%9D%B1%E4%BA%AC%E9%83%BD/%E6%AD%A6%E8%94%B5%E9%87%8E%E5%B8%82/%E3%81%84%E3%81%84%E3%81%AE%E3%81%8B%E3%81%97%E3%82%89",
      "price": 14800.0,
      "price_text": "14,800万円",
      "area": 80.76,
      "area_text": "80.76㎡・3LDK",
      "walk_minutes": 4,
      "walk_text": "吉祥寺駅 徒歩4分",
      "station": "吉祥寺",
      "age_years": null,
      "age_text": "",
      "image_url": "https://img.cowcamo.jp/uploads/report_gallery/url/663176/thumbnail_01.jpg",
      "address": "武蔵野市御殿山",
      "access": "吉祥寺駅徒歩4分"
    },
    {
      "source": "cowcamo",
      "type": "中古",
      "name": "レトロモダン建築で暮らす",
      "detail_url": "https://cowcamo.jp/%E6%9D%B1%E4%BA%AC%E9%83%BD/%E6%B8%8B%E8%B0%B7%E5%8C%BA/%E3%83%AC%E3%83%88%E3%83%AD%E3%83%A2%E3%83%80%E3%83%B3%E5%BB%BA%E7%AF%89%E3%81%A7%E6%9A%AE%E3%82%89%E3%81%99",
      "price": 24800.0,
      "price_text": "24,800万円",
      "area": 130.63,
      "area_text": "130.63㎡・4LDK",
      "walk_minutes": 5,
      "walk_text": "代々木駅 徒歩5分",
      "station": "代々木",
      "age_years": null,
      "age_text": "",
      "image_url": "https://img.cowcamo.jp/uploads/report_gallery/url/659579/thumbnail_05.jpg",
      "address": "渋谷区富ヶ谷",
      "access": "代々木公園駅徒歩5分"
    },
    {
      "source": "cowcamo",
      "type": "中古",
      "name": "",
      "detail_url": "https://cowcamo.jp/short_stories/8YymiLaX8Qc",
      "price": 16800.0,
      "price_text": "16,800万円",
      "area": 84.99,
      "area_text": "84.99㎡・3LDK",
      "walk_minutes": 5,
      "walk_text": "吉祥寺駅 徒歩5分",
      "station": "吉祥寺",
      "age_years": null,
      "age_text": "",
      "image_url": "https://img.cowcamo.jp/uploads/report_gallery/url/663712/thumbnail_20.jpg",
      "address": "武蔵野市吉祥寺本町",
      "access": "吉祥寺駅徒歩5分"
    },
    {
      "source": "cowcamo",
      "type": "中古",
      "name": "",
      "detail_url": "https://cowcamo.jp/short_stories/WIrWgTFF9D8",
      "price": 32500.0,
      "price_text": "32,500万円",
      "area": 251.92,
      "area_text": "251.92㎡・4LDK",
      "walk_minutes": 6,
      "walk_text": "吉祥寺駅 徒歩6分",
      "station": "吉祥寺",
      "age_years": null,
      "age_text": "",
      "image_url": "https://img.cowcamo.jp/uploads/report_gallery/url/661284/thumbnail_02.jpg",
      "address": "武蔵野市吉祥寺本町",
      "access": "吉祥寺駅徒歩6分"
    },
    {
      "source": "cowcamo",
      "type": "中古",
      "name": "",
      "detail_url": "https://cowcamo.jp/short_stories/4jQzro4UqhA",
      "price": 16200.0,
      "price_text": "16,200万円",
      "area": 96.43,
      "area_text": "96.43㎡・3SLDK",
      "walk_minutes": 3,
      "walk_text": "吉祥寺駅 徒歩3分",
      "station": "吉祥寺",
      "age_years": null,
      "age_text": "",
      "image_url": "https://img.cowcamo.jp/uploads/report_gallery/url/661174/thumbnail_02-1.jpg",
      "address": "武蔵野市吉祥寺南町",
      "access": "吉祥寺駅徒歩3分"
    }
  ]
}